<?xml version="1.0" encoding="ISO-8859-1"?>
<!DOCTYPE words SYSTEM "markables.dtd">
<markables xmlns="www.eml.org/NameSpaces/parse">
<markable id="markable_10001" span="word_1..word_2" tag="(S1 (NP (NN p.) (CD 87)))" mmax_level="parse" />
<markable id="markable_10002" span="word_3..word_36" tag="(S1 (S (NP (NP (ADJP (RB So) (HYPH -) (VBN called)) (NML (PP (`` '') (IN ON) (NP (NN programming)) ('' '')))) (: -) (VP (VBG meaning) (SBAR (IN that) (S (NP (NN series) (NNS episodes)) (VP (VBP are) (VP (VBN shot) (PP (ADVP (RB right)) (IN before) (NP (NP (DT the) (NN time)) (PP (IN of) (NP (NN broadcast)))))))))) (: -)) (VP (VBZ is) (NP (NP (DT a) (JJ special) (NN feature)) (PP (IN of) (NP (NP (NNP Taiwan) (POS 's)) (NML (JJ prime) (HYPH -) (NN time)) (VBN televised) (NNS serials))))) (. .)))" mmax_level="parse" />
<markable id="markable_10003" span="word_37..word_55" tag="(S1 (S (NP (DT The) (NN advantage)) (VP (VBZ is) (SBAR (IN that) (S (S (NP (DT the) (NN story)) (VP (MD can) (VP (VB be) (VP (VBN changed))))) (CC or) (S (NP (DT the) (NN series)) (VP (VBN extended) (CC or) (VBN shortened) (PP (VBG depending) (PP (IN upon) (NP (NNS ratings))))))))) (. .)))" mmax_level="parse" />
<markable id="markable_10004" span="word_56..word_63" tag="(S1 (S (NP (DT The) (NN disadvantage)) (VP (VBZ is) (SBAR (IN that) (S (NP (NN quality)) (VP (MD may) (VP (VB suffer)))))) (. .)))" mmax_level="parse" />
<markable id="markable_10005" span="word_64..word_88" tag="(S1 (S (NP (NP (DT The) (NN photo)) (ADVP (RB below))) (VP (VBZ shows) (NP (NP (DT the) (NN crew)) (PP (IN of) (NP (NP (DT the) (NNS series)) (S (NP (NNP Fortune)) (VP (VBZ is) (PP (IN in) (NP (NP (NNP Heaven) (POS 's)) (NNPS Hands))) (VP (VBG doing) (NP (DT an) (ADJP (RB all) (HYPH -) (JJ nighter))) (S (VP (TO to) (VP (VB complete) (NP (DT an) (NN episode)))))))))))) (. .)))" mmax_level="parse" />
<markable id="markable_10006" span="word_89..word_96" tag="(S1 (NP (-LRB- -LRB-) (NP (NN photo)) (PP (IN by) (NP (NNP Hsueh) (NNP Chi) (HYPH -) (NNP kuang))) (-RRB- -RRB-)))" mmax_level="parse" />
<markable id="markable_10007" span="word_97..word_98" tag="(S1 (NP (NN p.) (CD 88)))" mmax_level="parse" />
<markable id="markable_10008" span="word_99..word_129" tag="(S1 (S (NP (NP (NP (DT The) (NN series)) (NP (NNP Love))) (, ,) (VP (VBN broadcast) (PP (IN by) (NP (NNP CTS))) (PP (IN in) (NP (CD 1983)))) (, ,)) (VP (VP (VBD was) (NP (NP (DT the) (JJ first) (NML (JJ prime) (HYPH -) (NN time)) (NN drama)) (S (VP (TO to) (VP (VB use) (NP (NNP Taiwanese))))))) (, ,) (CC and) (VP (VBD marked) (NP (DT a) (JJ new) (NN beginning)) (PP (IN for) (NP (JJ Taiwanese) (JJ nativist) (NN drama))))) (. .)))" mmax_level="parse" />
<markable id="markable_10009" span="word_130..word_170" tag="(S1 (S (NP (DT The) (NN photo)) (VP (VBZ shows) (NP (NP (DT the) (NNS performers)) (SBAR (WHNP (WP who)) (S (VP (VBD played) (NP (NP (DT the) (CD two) (JJ main) (NNS couples)) (PP (IN in) (NP (DT the) (NN series))) (, ,) (PP (IN from) (NP (NP (JJ left)) (SBAR (S (VP (TO to) (VP (VB write) (NP (NP (: :) (NNP Ma) (NNP Ju) (HYPH -) (NNP feng)) (, ,) (NP (NP (NNP Chang) (NNP Chiung) (HYPH -) (NNP tsu)) (, ,) (NP (NNP Chin) (NNP Su) (HYPH -) (NNP mei))) (, ,) (CC and) (NP (NNP Liu) (NNP Teh) (HYPH -) (NNP kai))))))))))))))) (. .)))" mmax_level="parse" />
<markable id="markable_10010" span="word_171..word_178" tag="(S1 (NP (-LRB- -LRB-) (NP (NN photo)) (PP (IN by) (NP (NNP Tsai) (NNP Sen) (HYPH -) (NNP chi))) (-RRB- -RRB-)))" mmax_level="parse" />
<markable id="markable_10011" span="word_179..word_180" tag="(S1 (NP (NN p.) (CD 89)))" mmax_level="parse" />
<markable id="markable_10012" span="word_181..word_196" tag="(S1 (S (PP (IN With) (NP (NP (DT the) (NN popularity)) (PP (IN of) (NP (JJ nativist) (JJ Taiwanese) (NN drama))))) (, ,) (NP (ADJP (NNP Taiwanese) (HYPH -) (VBG speaking)) (NNS performers)) (VP (VBP are) (PP (IN in) (NP (NN demand)))) (. .)))" mmax_level="parse" />
<markable id="markable_10013" span="word_197..word_217" tag="(S1 (SINV (ADJP (JJ Such)) (VP (VBZ is)) (NP (NP (DT the) (NN case)) (PP (IN with) (NP (NP (NML (JJ veteran) (NN actor)) (NNP Shih) (NNP Ying)) (, ,) (SBAR (WHNP (WP who)) (S (VP (VBZ is) (ADVP (RB now)) (VP (VBN featured) (PP (IN in) (NP (NP (DT the) (NNP CTS) (NN series)) (NP (NNP First) (NNP Family))))))))))) (. .)))" mmax_level="parse" />
<markable id="markable_10014" span="word_218..word_225" tag="(S1 (NP (-LRB- -LRB-) (NP (NN photo)) (PP (IN by) (NP (NNP Tsai) (NNP Sen) (HYPH -) (NNP chi))) (-RRB- -RRB-)))" mmax_level="parse" />
<markable id="markable_10015" span="word_226..word_227" tag="(S1 (NP (NN p.) (CD 90)))" mmax_level="parse" />
<markable id="markable_10016" span="word_228..word_255" tag="(S1 (S (NP (NP (NNP Chang) (NNP Yu)) (: -) (NP (NP (NNS yen)) (PRN (-LRB- -LRB-) (ADVP (RB right)) (-RRB- -RRB-)))) (VP (VBZ plays) (NP (DT a) (NML (NML (ADJP (RB much) (HYPH -) (VBN abused)) (NN daughter)) (HYPH -) (PP (IN in) (HYPH -) (NP (NN law))))) (PP (IN in) (NP (NP (DT the) (NN series)) (NP (DT The) (NML (NML (JJ Astonishing) (NN Daughter)) (HYPH -) (PP (IN in) (HYPH -) (NP (NN Law)))))))) (. .)))" mmax_level="parse" />
<markable id="markable_10017" span="word_256..word_267" tag="(S1 (S (NP (PRP$ Her) (JJ pitiable) (NN character)) (VP (VBZ has) (VP (VBD resonated) (PP (IN with) (NP (JJ many) (ADJP (NN middle) (HYPH -) (JJ aged)) (NNS women))))) (. .)))" mmax_level="parse" />
<markable id="markable_10018" span="word_268..word_275" tag="(S1 (NP (-LRB- -LRB-) (NP (NN photo)) (PP (IN by) (NP (NNP Tsai) (NNP Sen) (HYPH -) (NNP chi))) (-RRB- -RRB-)))" mmax_level="parse" />
<markable id="markable_10019" span="word_276..word_277" tag="(S1 (NP (NN [.) (CD 91)))" mmax_level="parse" />
<markable id="markable_10020" span="word_278..word_311" tag="(S1 (S (NP (NP (DT The) (JJ Taiwanese) (`` '') (JJ contemporary) (NN drama) ('' '')) (VP (VBG being) (VP (VBN shown) (PP (IN by) (NP (NNP Formosa) (NNP Television))) (PP (IN in) (NP (PRP$ its) (CD 8:00) (NN time) (NN slot)))))) (VP (VBZ has) (VP (VBN maintained) (NP (ADJP (RB very) (JJ high)) (NNS ratings)) (, ,) (S (VP (VBG pulling) (NP (DT the) (NN station)) (PP (IN out) (PP (IN of) (NP (DT the) (NN red))) (CC and) (PP (IN into) (NP (DT the) (NN black)))))))) (. .)))" mmax_level="parse" />
<markable id="markable_10021" span="word_312..word_324" tag="(S1 (S (NP (DT The) (NN photo)) (VP (VBZ is) (PP (IN from) (NP (NP (DT the) (NN series)) (S (NP (NNP Fortune)) (VP (VBZ is) (PP (IN in) (NP (NP (NNP Heaven) (POS 's)) (NNPS Hands)))))))) (. .)))" mmax_level="parse" />
<markable id="markable_10022" span="word_325..word_332" tag="(S1 (NP (-LRB- -LRB-) (NP (NN courtesy)) (PP (IN of) (NP (NML (NML (NN series)) (NN producer)) (NNP April) (NNP Chu))) (-RRB- -RRB-)))" mmax_level="parse" />
<markable id="markable_10023" span="word_333..word_334" tag="(S1 (NP (NN p.) (CD 93)))" mmax_level="parse" />
<markable id="markable_10024" span="word_335..word_359" tag="(S1 (S (NP (EX There)) (VP (VBZ has) (VP (VBN been) (VP (VBG growing) (NP (NP (NN cooperation)) (PP (IN between) (NP (NP (DT the) (NN TV) (NNS industries)) (PP (IN of) (NP (NP (NNP Taiwan)) (, ,) (NP (NNP Hong) (NNP Kong)) (, ,) (CC and) (NP (NN mainland) (NNP China))))))) (PP (IN in) (S (VP (VBG producing) (NP (NML (JJ prime) (HYPH -) (NN time)) (NN programming)))))))) (. .)))" mmax_level="parse" />
<markable id="markable_10025" span="word_360..word_398" tag="(S1 (S (PP (IN In) (NP (NP (NP (DT the) (NN series)) (NP (NNP White) (JJ Haired) (NNP Sorceress))) (VP (VP (VBN broadcast) (PP (IN on) (NP (NNP TTV)))) (CC and) (VP (VBN produced) (PP (IN by) (NP (NNP Chou) (NNP You))))))) (, ,) (NP (NP (DT the) (JJ male) (NN lead)) (, ,) (NP (NNP Zhang) (NNP Zhilin)) (, ,)) (VP (VP (VBD was) (PP (IN from) (NP (NNP Hong) (NNP Kong)))) (, ,) (CC and) (VP (NP (NP (DT the) (JJ female) (NN lead)) (, ,) (NP (NNP Shui) (NNP Ling)) (, ,)) (PP (IN from) (NP (DT the) (NNP PRC))))) (. .)))" mmax_level="parse" />
<markable id="markable_10026" span="word_399..word_404" tag="(S1 (NP (-LRB- -LRB-) (NP (NN courtesy)) (PP (IN of) (NP (NNP Chou) (NNP You))) (-RRB- -RRB-)))" mmax_level="parse" />
<markable id="markable_10027" span="word_405..word_406" tag="(S1 (NP (NN p.) (CD 93)))" mmax_level="parse" />
<markable id="markable_10028" span="word_407..word_415" tag="(S1 (S (NP (NP (NNP Chiung) (NNP Yao) (POS 's)) (NNS romances)) (VP (VBP have) (NP (PRP$ their) (JJ own) (NN style))) (. .)))" mmax_level="parse" />
<markable id="markable_10029" span="word_416..word_430" tag="(S1 (S (NP (PRP They)) (VP (VP (VBP offer) (NP (JJ intense) (NNS plots) (CC and) (NN dialogue))) (CC and) (ADVP (RB always)) (VP (VBP feature) (NP (JJ attractive) (VBG leading) (NNS men) (CC and) (NNS women)))) (. .)))" mmax_level="parse" />
<markable id="markable_10030" span="word_431..word_468" tag="(S1 (S (NP (DT The) (NN photo)) (VP (VBZ shows) (NP (NP (NML (NN mainland) (NN actress)) (NNP Zhao) (NNP Wei) (PRN (-LRB- -LRB-) (ADVP (RB left)) (-RRB- -RRB-))) (, ,) (SBAR (WHNP (WP who)) (S (VP (VBD became) (ADJP (JJ popular) (PP (IN throughout) (NP (DT the) (JJ Chinese) (NN world)))) (PP (IN after) (S (VP (VBG starring) (PP (IN in) (NP (DT a) (NML (NNP Chiung) (NNP Yao)) (NN series)))))) (, ,) (PP (VBN pictured) (PP (IN with) (NP (NP (JJ former) (NN child) (NN star)) (NP (NNP Su) (NNP You) (HYPH -) (NNP peng)) (PP (IN of) (NP (NNP Taiwan))))))))))) (. .)))" mmax_level="parse" />
<markable id="markable_10031" span="word_469..word_475" tag="(S1 (NP (-LRB- -LRB-) (NP (NN courtesy)) (PP (IN of) (NP (NML (NNP Joy) (NNP Production)) (NNP Corporation))) (-RRB- -RRB-)))" mmax_level="parse" />
<markable id="markable_10032" span="word_476..word_477" tag="(S1 (NP (NN p.) (CD 93)))" mmax_level="parse" />
<markable id="markable_10033" span="word_478..word_506" tag="(S1 (S (NP (NP (NP (DT The) (NN series)) (NP (NP (DT An) (NN Official) (POS 's)) (NN Wife))) (, ,) (VP (VBN produced) (PP (IN by) (NP (NNP Chou) (NNP You)))) (, ,)) (VP (VBD brought) (ADVP (RB together)) (NP (NP (NP (JJ Taiwanese) (NN performer)) (NP (NNP Chen) (NNP Ya) (HYPH -) (NNP lan) (PRN (-LRB- -LRB-) (ADVP (RB left)) (-RRB- -RRB-)))) (CC and) (NP (NML (NN mainland) (NN star)) (NNP Zhang) (NNP Guoli)))) (. .)))" mmax_level="parse" />
<markable id="markable_10034" span="word_507..word_517" tag="(S1 (S (NP (NP (PRP$ Their) (JJ different) (NNS accents)) (CC and) (NP (VBG acting) (NNS styles))) (VP (VBD created) (NP (JJ many) (NN comic) (NNS opportunities))) (. .)))" mmax_level="parse" />
<markable id="markable_10035" span="word_518..word_523" tag="(S1 (NP (-LRB- -LRB-) (NP (NN courtesy)) (PP (IN of) (NP (NNP Chou) (NNP You))) (-RRB- -RRB-)))" mmax_level="parse" />
</markables>
