<?xml version="1.0" encoding="ISO-8859-1"?>
<!DOCTYPE words SYSTEM "words.dtd">
<words>
  <word id="word_1">Abfahren</word>
  <word id="word_2">leichtgemacht</word>
  <word id="word_3">Künstliche</word>
  <word id="word_4">,</word>
  <word id="word_5">abgeschirmte</word>
  <word id="word_6">Idyllen</word>
  <word id="word_7">sind</word>
  <word id="word_8">der</word>
  <word id="word_9">Erfolgsschlager</word>
  <word id="word_10">im</word>
  <word id="word_11">Tourismus</word>
  <word id="word_12">:</word>
  <word id="word_13">angebotssatt</word>
  <word id="word_14">,</word>
  <word id="word_15">befriedet</word>
  <word id="word_16">und</word>
  <word id="word_17">spaßig</word>
  <word id="word_18">.</word>
  <word id="word_19">Sie</word>
  <word id="word_20">sollen</word>
  <word id="word_21">sogar</word>
  <word id="word_22">Natur</word>
  <word id="word_23">und</word>
  <word id="word_24">Kultur</word>
  <word id="word_25">schützen</word>
  <word id="word_26">.</word>
  <word id="word_27">Wir</word>
  <word id="word_28">fragen</word>
  <word id="word_29">wie</word>
  <word id="word_30">Von</word>
  <word id="word_31">Christel</word>
  <word id="word_32">Burghoff</word>
  <word id="word_33">und</word>
  <word id="word_34">Edith</word>
  <word id="word_35">Kresta</word>
  <word id="word_36">Die</word>
  <word id="word_37">Welt</word>
  <word id="word_38">ist</word>
  <word id="word_39">klein</word>
  <word id="word_40">geworden</word>
  <word id="word_41">.</word>
  <word id="word_42">Nach</word>
  <word id="word_43">der</word>
  <word id="word_44">erfolgreichen</word>
  <word id="word_45">Landung</word>
  <word id="word_46">in</word>
  <word id="word_47">Thailand</word>
  <word id="word_48">,</word>
  <word id="word_49">Kenia</word>
  <word id="word_50">,</word>
  <word id="word_51">Malaga</word>
  <word id="word_52">bricht</word>
  <word id="word_53">der</word>
  <word id="word_54">Tourismus</word>
  <word id="word_55">zu</word>
  <word id="word_56">neuen</word>
  <word id="word_57">Ufern</word>
  <word id="word_58">auf</word>
  <word id="word_59">.</word>
  <word id="word_60">Die</word>
  <word id="word_61">Simulation</word>
  <word id="word_62">macht</word>
  <word id="word_63">'s</word>
  <word id="word_64">möglich</word>
  <word id="word_65">.</word>
  <word id="word_66">Sei</word>
  <word id="word_67">'s</word>
  <word id="word_68">als</word>
  <word id="word_69">Arche</word>
  <word id="word_70">Noah</word>
  <word id="word_71">vor</word>
  <word id="word_72">der</word>
  <word id="word_73">Haustür</word>
  <word id="word_74">,</word>
  <word id="word_75">als</word>
  <word id="word_76">traute</word>
  <word id="word_77">Heimat</word>
  <word id="word_78">im</word>
  <word id="word_79">fernen</word>
  <word id="word_80">Paradiesgärtchen</word>
  <word id="word_81">-</word>
  <word id="word_82">das</word>
  <word id="word_83">Erdenglück</word>
  <word id="word_84">wird</word>
  <word id="word_85">rundum</word>
  <word id="word_86">fabriziert</word>
  <word id="word_87">.</word>
  <word id="word_88">Im</word>
  <word id="word_89">touristischen</word>
  <word id="word_90">Ghetto</word>
  <word id="word_91">feiert</word>
  <word id="word_92">es</word>
  <word id="word_93">fröhliche</word>
  <word id="word_94">Urständ</word>
  <word id="word_95">.</word>
  <word id="word_96">Wo</word>
  <word id="word_97">sonst</word>
  <word id="word_98">lassen</word>
  <word id="word_99">sich</word>
  <word id="word_100">Urlauberbedürfnisse</word>
  <word id="word_101">so</word>
  <word id="word_102">komprimiert</word>
  <word id="word_103">aufbereiten</word>
  <word id="word_104">?</word>
  <word id="word_105">"</word>
  <word id="word_106">Ich</word>
  <word id="word_107">bin</word>
  <word id="word_108">dieses</word>
  <word id="word_109">Jahr</word>
  <word id="word_110">ganz</word>
  <word id="word_111">erschöpft</word>
  <word id="word_112">in</word>
  <word id="word_113">den</word>
  <word id="word_114">Urlaub</word>
  <word id="word_115">gefahren</word>
  <word id="word_116">.</word>
  <word id="word_117">Und</word>
  <word id="word_118">in</word>
  <word id="word_119">meiner</word>
  <word id="word_120">Erschöpfung</word>
  <word id="word_121">brauche</word>
  <word id="word_122">ich</word>
  <word id="word_123">den</word>
  <word id="word_124">Schutz</word>
  <word id="word_125">,</word>
  <word id="word_126">die</word>
  <word id="word_127">Sicherheit</word>
  <word id="word_128">,</word>
  <word id="word_129">das</word>
  <word id="word_130">Versorgtwerden</word>
  <word id="word_131">.</word>
  <word id="word_132">Die</word>
  <word id="word_133">gute</word>
  <word id="word_134">Organisation</word>
  <word id="word_135">meines</word>
  <word id="word_136">Veranstalters</word>
  <word id="word_137">hat</word>
  <word id="word_138">mir</word>
  <word id="word_139">schon</word>
  <word id="word_140">während</word>
  <word id="word_141">der</word>
  <word id="word_142">Reise</word>
  <word id="word_143">die</word>
  <word id="word_144">erste</word>
  <word id="word_145">Gelassenheit</word>
  <word id="word_146">ermöglicht</word>
  <word id="word_147">;</word>
  <word id="word_148">Pannen</word>
  <word id="word_149">,</word>
  <word id="word_150">Störungen</word>
  <word id="word_151">,</word>
  <word id="word_152">Konflikte</word>
  <word id="word_153">hätte</word>
  <word id="word_154">ich</word>
  <word id="word_155">nur</word>
  <word id="word_156">schlecht</word>
  <word id="word_157">ertragen</word>
  <word id="word_158">...</word>
  <word id="word_159">Mein</word>
  <word id="word_160">Touristenghetto</word>
  <word id="word_161">präsentiert</word>
  <word id="word_162">mir</word>
  <word id="word_163">das</word>
  <word id="word_164">Grandiose</word>
  <word id="word_165">,</word>
  <word id="word_166">das</word>
  <word id="word_167">Irritierende</word>
  <word id="word_168">der</word>
  <word id="word_169">fremden</word>
  <word id="word_170">südlichen</word>
  <word id="word_171">Welt</word>
  <word id="word_172">portioniert</word>
  <word id="word_173">,</word>
  <word id="word_174">verkleinert</word>
  <word id="word_175">und</word>
  <word id="word_176">überschaubar</word>
  <word id="word_177">.</word>
  <word id="word_178">"</word>
  <word id="word_179">Die</word>
  <word id="word_180">Pädagogin</word>
  <word id="word_181">Gisela</word>
  <word id="word_182">Wegener-Spöhring</word>
  <word id="word_183">spricht</word>
  <word id="word_184">in</word>
  <word id="word_185">ihrem</word>
  <word id="word_186">Buch</word>
  <word id="word_187">"</word>
  <word id="word_188">Massentourismus</word>
  <word id="word_189">und</word>
  <word id="word_190">Pädagogik</word>
  <word id="word_191">"</word>
  <word id="word_192">aus</word>
  <word id="word_193">,</word>
  <word id="word_194">was</word>
  <word id="word_195">die</word>
  <word id="word_196">abgeschlossene</word>
  <word id="word_197">Anlage</word>
  <word id="word_198">so</word>
  <word id="word_199">attraktiv</word>
  <word id="word_200">macht</word>
  <word id="word_201">:</word>
  <word id="word_202">aufgehoben</word>
  <word id="word_203">und</word>
  <word id="word_204">versorgt</word>
  <word id="word_205">,</word>
  <word id="word_206">geschätzt</word>
  <word id="word_207">,</word>
  <word id="word_208">hofiert</word>
  <word id="word_209">und</word>
  <word id="word_210">angenommen</word>
  <word id="word_211">zu</word>
  <word id="word_212">sein</word>
  <word id="word_213">.</word>
  <word id="word_214">"</word>
  <word id="word_215">Wann</word>
  <word id="word_216">habe</word>
  <word id="word_217">ich</word>
  <word id="word_218">das</word>
  <word id="word_219">sonst</word>
  <word id="word_220">je</word>
  <word id="word_221">?</word>
  <word id="word_222">Ich</word>
  <word id="word_223">weiß</word>
  <word id="word_224">,</word>
  <word id="word_225">daß</word>
  <word id="word_226">ich</word>
  <word id="word_227">dies</word>
  <word id="word_228">alles</word>
  <word id="word_229">bezahle</word>
  <word id="word_230">,</word>
  <word id="word_231">aber</word>
  <word id="word_232">ich</word>
  <word id="word_233">nehme</word>
  <word id="word_234">es</word>
  <word id="word_235">aufatmend</word>
  <word id="word_236">an</word>
  <word id="word_237">.</word>
  <word id="word_238">"</word>
  <word id="word_239">Ein</word>
  <word id="word_240">Seufzer</word>
  <word id="word_241">,</word>
  <word id="word_242">die</word>
  <word id="word_243">Urlauberin</word>
  <word id="word_244">fühlt</word>
  <word id="word_245">sich</word>
  <word id="word_246">entlastet</word>
  <word id="word_247">,</word>
  <word id="word_248">sie</word>
  <word id="word_249">spürt</word>
  <word id="word_250">,</word>
  <word id="word_251">ihre</word>
  <word id="word_252">Bedürfnisse</word>
  <word id="word_253">sind</word>
  <word id="word_254">ihr</word>
  <word id="word_255">vorausgeeilt</word>
  <word id="word_256">.</word>
  <word id="word_257">Frau</word>
  <word id="word_258">Wegener-Spöhring</word>
  <word id="word_259">ist</word>
  <word id="word_260">eine</word>
  <word id="word_261">Urlauberin</word>
  <word id="word_262">im</word>
  <word id="word_263">Trend</word>
  <word id="word_264">der</word>
  <word id="word_265">Zeit</word>
  <word id="word_266">.</word>
  <word id="word_267">Sie</word>
  <word id="word_268">kauft</word>
  <word id="word_269">pauschal</word>
  <word id="word_270">,</word>
  <word id="word_271">ein</word>
  <word id="word_272">gut</word>
  <word id="word_273">geschnürtes</word>
  <word id="word_274">Urlaubspaket</word>
  <word id="word_275">,</word>
  <word id="word_276">wie</word>
  <word id="word_277">immer</word>
  <word id="word_278">mehr</word>
  <word id="word_279">deutsche</word>
  <word id="word_280">Urlauber</word>
  <word id="word_281">.</word>
  <word id="word_282">Sie</word>
  <word id="word_283">ist</word>
  <word id="word_284">keine</word>
  <word id="word_285">dieser</word>
  <word id="word_286">Massentouristen</word>
  <word id="word_287">,</word>
  <word id="word_288">denen</word>
  <word id="word_289">nachgesagt</word>
  <word id="word_290">wird</word>
  <word id="word_291">,</word>
  <word id="word_292">daß</word>
  <word id="word_293">sie</word>
  <word id="word_294">wie</word>
  <word id="word_295">Heuschrecken</word>
  <word id="word_296">über</word>
  <word id="word_297">fremde</word>
  <word id="word_298">Länder</word>
  <word id="word_299">herfallen</word>
  <word id="word_300">.</word>
  <word id="word_301">Sie</word>
  <word id="word_302">geht</word>
  <word id="word_303">gleich</word>
  <word id="word_304">in</word>
  <word id="word_305">die</word>
  <word id="word_306">abgeschirmte</word>
  <word id="word_307">Großanlage</word>
  <word id="word_308">.</word>
  <word id="word_309">Sie</word>
  <word id="word_310">beschränkt</word>
  <word id="word_311">sich</word>
  <word id="word_312">auf</word>
  <word id="word_313">das</word>
  <word id="word_314">kleine</word>
  <word id="word_315">für</word>
  <word id="word_316">sie</word>
  <word id="word_317">aufbereitete</word>
  <word id="word_318">Stück</word>
  <word id="word_319">vom</word>
  <word id="word_320">Paradies</word>
  <word id="word_321">.</word>
  <word id="word_322">Ghettos</word>
  <word id="word_323">sind</word>
  <word id="word_324">der</word>
  <word id="word_325">klare</word>
  <word id="word_326">Trend</word>
  <word id="word_327">in</word>
  <word id="word_328">der</word>
  <word id="word_329">touristischen</word>
  <word id="word_330">Entwicklung</word>
  <word id="word_331">.</word>
  <word id="word_332">Exportschlager</word>
  <word id="word_333">touristisches</word>
  <word id="word_334">Ghetto</word>
  <word id="word_335">Hierzulande</word>
  <word id="word_336">sind</word>
  <word id="word_337">vor</word>
  <word id="word_338">allem</word>
  <word id="word_339">die</word>
  <word id="word_340">Anbieter</word>
  <word id="word_341">überglaster</word>
  <word id="word_342">Wasserlandschaften</word>
  <word id="word_343">und</word>
  <word id="word_344">Freizeitzentren</word>
  <word id="word_345">aktiv</word>
  <word id="word_346">.</word>
  <word id="word_347">Gleich</word>
  <word id="word_348">drei</word>
  <word id="word_349">Großanbieter</word>
  <word id="word_350">drängen</word>
  <word id="word_351">auf</word>
  <word id="word_352">den</word>
  <word id="word_353">deutschen</word>
  <word id="word_354">Markt</word>
  <word id="word_355">:</word>
  <word id="word_356">Center</word>
  <word id="word_357">Parcs</word>
  <word id="word_358">,</word>
  <word id="word_359">Gran</word>
  <word id="word_360">Dorado</word>
  <word id="word_361">und</word>
  <word id="word_362">Sun</word>
  <word id="word_363">Parks</word>
  <word id="word_364">.</word>
  <word id="word_365">Alle</word>
  <word id="word_366">haben</word>
  <word id="word_367">ihr</word>
  <word id="word_368">verglastes</word>
  <word id="word_369">Ferienprodukt</word>
  <word id="word_370">bereits</word>
  <word id="word_371">in</word>
  <word id="word_372">den</word>
  <word id="word_373">Niederlanden</word>
  <word id="word_374">,</word>
  <word id="word_375">aber</word>
  <word id="word_376">auch</word>
  <word id="word_377">in</word>
  <word id="word_378">England</word>
  <word id="word_379">und</word>
  <word id="word_380">Frankreich</word>
  <word id="word_381">erfolgreich</word>
  <word id="word_382">vermarktet</word>
  <word id="word_383">.</word>
  <word id="word_384">Im</word>
  <word id="word_385">Ferntourismus</word>
  <word id="word_386">ist</word>
  <word id="word_387">dieses</word>
  <word id="word_388">Konzept</word>
  <word id="word_389">der</word>
  <word id="word_390">abgesicherten</word>
  <word id="word_391">,</word>
  <word id="word_392">autarken</word>
  <word id="word_393">Anlage</word>
  <word id="word_394">ohnehin</word>
  <word id="word_395">gängige</word>
  <word id="word_396">Praxis</word>
  <word id="word_397">.</word>
  <word id="word_398">Der</word>
  <word id="word_399">französische</word>
  <word id="word_400">Marktvorreiter</word>
  <word id="word_401">Club</word>
  <word id="word_402">Mediterranee</word>
  <word id="word_403">hat</word>
  <word id="word_404">schon</word>
  <word id="word_405">jetzt</word>
  <word id="word_406">stolze</word>
  <word id="word_407">110</word>
  <word id="word_408">Dörfer</word>
  <word id="word_409">weltweit</word>
  <word id="word_410">.</word>
  <word id="word_411">Die</word>
  <word id="word_412">TUI</word>
  <word id="word_413">besitzt</word>
  <word id="word_414">derzeit</word>
  <word id="word_415">27</word>
  <word id="word_416">Robinson-Clubs</word>
  <word id="word_417">,</word>
  <word id="word_418">die</word>
  <word id="word_419">Robinson-Konkurrentin</word>
  <word id="word_420">auf</word>
  <word id="word_421">dem</word>
  <word id="word_422">deutschen</word>
  <word id="word_423">Markt</word>
  <word id="word_424">,</word>
  <word id="word_425">Aldiana</word>
  <word id="word_426">(</word>
  <word id="word_427">NUR</word>
  <word id="word_428">)</word>
  <word id="word_429">,</word>
  <word id="word_430">hat</word>
  <word id="word_431">12</word>
  <word id="word_432">Anlagen</word>
  <word id="word_433">.</word>
  <word id="word_434">Nicht</word>
  <word id="word_435">nur</word>
  <word id="word_436">Clubs</word>
  <word id="word_437">,</word>
  <word id="word_438">sondern</word>
  <word id="word_439">abgeschlossene</word>
  <word id="word_440">Ferienanlagen</word>
  <word id="word_441">allgemein</word>
  <word id="word_442">sind</word>
  <word id="word_443">weltweit</word>
  <word id="word_444">im</word>
  <word id="word_445">Kommen</word>
  <word id="word_446">.</word>
  <word id="word_447">Ob</word>
  <word id="word_448">in</word>
  <word id="word_449">Deutschland</word>
  <word id="word_450">oder</word>
  <word id="word_451">der</word>
  <word id="word_452">Türkei</word>
  <word id="word_453">,</word>
  <word id="word_454">wo</word>
  <word id="word_455">die</word>
  <word id="word_456">Südküste</word>
  <word id="word_457">immer</word>
  <word id="word_458">weiter</word>
  <word id="word_459">ausgebaut</word>
  <word id="word_460">wird</word>
  <word id="word_461">,</word>
  <word id="word_462">in</word>
  <word id="word_463">Tunesien</word>
  <word id="word_464">,</word>
  <word id="word_465">wo</word>
  <word id="word_466">nun</word>
  <word id="word_467">der</word>
  <word id="word_468">strukturschwache</word>
  <word id="word_469">Norden</word>
  <word id="word_470">und</word>
  <word id="word_471">die</word>
  <word id="word_472">Oasen</word>
  <word id="word_473">im</word>
  <word id="word_474">Landesinnern</word>
  <word id="word_475">mit</word>
  <word id="word_476">Luxusenklaven</word>
  <word id="word_477">überzogen</word>
  <word id="word_478">werden</word>
  <word id="word_479">-</word>
  <word id="word_480">abgeschlossene</word>
  <word id="word_481">Areale</word>
  <word id="word_482">mit</word>
  <word id="word_483">einer</word>
  <word id="word_484">Vielzahl</word>
  <word id="word_485">von</word>
  <word id="word_486">Beschäftigungs-</word>
  <word id="word_487">und</word>
  <word id="word_488">Amüsierangeboten</word>
  <word id="word_489">vom</word>
  <word id="word_490">Golfplatz</word>
  <word id="word_491">bis</word>
  <word id="word_492">zur</word>
  <word id="word_493">Animiermeile</word>
  <word id="word_494">beherrschen</word>
  <word id="word_495">nicht</word>
  <word id="word_496">nur</word>
  <word id="word_497">die</word>
  <word id="word_498">Strände</word>
  <word id="word_499">unserer</word>
  <word id="word_500">Erde</word>
  <word id="word_501">.</word>
  <word id="word_502">In</word>
  <word id="word_503">den</word>
  <word id="word_504">von</word>
  <word id="word_505">Krediten</word>
  <word id="word_506">gebeutelten</word>
  <word id="word_507">und</word>
  <word id="word_508">devisenabhängigen</word>
  <word id="word_509">Ländern</word>
  <word id="word_510">der</word>
  <word id="word_511">Dritten</word>
  <word id="word_512">Welt</word>
  <word id="word_513">schlägt</word>
  <word id="word_514">der</word>
  <word id="word_515">kapitalkräftige</word>
  <word id="word_516">Großtourismus</word>
  <word id="word_517">ausländischer</word>
  <word id="word_518">Konzerne</word>
  <word id="word_519">alle</word>
  <word id="word_520">Konkurrenten</word>
  <word id="word_521">.</word>
  <word id="word_522">Vom</word>
  <word id="word_523">einheimischen</word>
  <word id="word_524">Bauern</word>
  <word id="word_525">bis</word>
  <word id="word_526">zum</word>
  <word id="word_527">einheimischen</word>
  <word id="word_528">Investor</word>
  <word id="word_529">.</word>
  <word id="word_530">Er</word>
  <word id="word_531">hat</word>
  <word id="word_532">die</word>
  <word id="word_533">Mittel</word>
  <word id="word_534">für</word>
  <word id="word_535">aufwendige</word>
  <word id="word_536">Investitionen</word>
  <word id="word_537">und</word>
  <word id="word_538">für</word>
  <word id="word_539">die</word>
  <word id="word_540">Entwicklung</word>
  <word id="word_541">der</word>
  <word id="word_542">touristischen</word>
  <word id="word_543">Infrastruktur</word>
  <word id="word_544">auf</word>
  <word id="word_545">modernstem</word>
  <word id="word_546">technischem</word>
  <word id="word_547">Stand</word>
  <word id="word_548">,</word>
  <word id="word_549">das</word>
  <word id="word_550">Know-how</word>
  <word id="word_551">und</word>
  <word id="word_552">vor</word>
  <word id="word_553">allem</word>
  <word id="word_554">den</word>
  <word id="word_555">Vertrieb</word>
  <word id="word_556">.</word>
  <word id="word_557">Ein</word>
  <word id="word_558">ausländischer</word>
  <word id="word_559">Großanbieter</word>
  <word id="word_560">bringt</word>
  <word id="word_561">internationale</word>
  <word id="word_562">Erfahrung</word>
  <word id="word_563">mit</word>
  <word id="word_564">und</word>
  <word id="word_565">verfügt</word>
  <word id="word_566">über</word>
  <word id="word_567">ein</word>
  <word id="word_568">ausgebautes</word>
  <word id="word_569">Marketing</word>
  <word id="word_570">.</word>
  <word id="word_571">Und</word>
  <word id="word_572">er</word>
  <word id="word_573">bringt</word>
  <word id="word_574">die</word>
  <word id="word_575">zur</word>
  <word id="word_576">Schuldenrückzahlung</word>
  <word id="word_577">dringend</word>
  <word id="word_578">benötigten</word>
  <word id="word_579">Devisen</word>
  <word id="word_580">ins</word>
  <word id="word_581">Land</word>
  <word id="word_582">.</word>
  <word id="word_583">Kein</word>
  <word id="word_584">Wunder</word>
  <word id="word_585">,</word>
  <word id="word_586">daß</word>
  <word id="word_587">in</word>
  <word id="word_588">fast</word>
  <word id="word_589">allen</word>
  <word id="word_590">Ländern</word>
  <word id="word_591">der</word>
  <word id="word_592">Dritten</word>
  <word id="word_593">Welt</word>
  <word id="word_594">die</word>
  <word id="word_595">Prioritäten</word>
  <word id="word_596">der</word>
  <word id="word_597">kapitalkräftigen</word>
  <word id="word_598">touristischen</word>
  <word id="word_599">Investoren</word>
  <word id="word_600">auch</word>
  <word id="word_601">die</word>
  <word id="word_602">Prioritäten</word>
  <word id="word_603">der</word>
  <word id="word_604">Regierung</word>
  <word id="word_605">sind</word>
  <word id="word_606">.</word>
  <word id="word_607">Geradezu</word>
  <word id="word_608">"</word>
  <word id="word_609">naturwüchsig</word>
  <word id="word_610">"</word>
  <word id="word_611">entsteht</word>
  <word id="word_612">so</word>
  <word id="word_613">in</word>
  <word id="word_614">Ländern</word>
  <word id="word_615">der</word>
  <word id="word_616">Dritten</word>
  <word id="word_617">Welt</word>
  <word id="word_618">ein</word>
  <word id="word_619">standardisierter</word>
  <word id="word_620">Großtourismus</word>
  <word id="word_621">.</word>
  <word id="word_622">Das</word>
  <word id="word_623">Nonplusultra</word>
  <word id="word_624">ist</word>
  <word id="word_625">die</word>
  <word id="word_626">Luxusenklave</word>
  <word id="word_627">-</word>
  <word id="word_628">optimierte</word>
  <word id="word_629">Freizone</word>
  <word id="word_630">für</word>
  <word id="word_631">Touristen</word>
  <word id="word_632">.</word>
  <word id="word_633">Sie</word>
  <word id="word_634">ist</word>
  <word id="word_635">die</word>
  <word id="word_636">logische</word>
  <word id="word_637">Folge</word>
  <word id="word_638">einer</word>
  <word id="word_639">expandierenden</word>
  <word id="word_640">,</word>
  <word id="word_641">kapitalintensiven</word>
  <word id="word_642">Industrie</word>
  <word id="word_643">.</word>
  <word id="word_644">Schützen</word>
  <word id="word_645">Ghettos</word>
  <word id="word_646">die</word>
  <word id="word_647">Natur</word>
  <word id="word_648">?</word>
  <word id="word_649">Für</word>
  <word id="word_650">viele</word>
  <word id="word_651">ist</word>
  <word id="word_652">sie</word>
  <word id="word_653">aber</word>
  <word id="word_654">mehr</word>
  <word id="word_655">.</word>
  <word id="word_656">Zum</word>
  <word id="word_657">Beispiel</word>
  <word id="word_658">für</word>
  <word id="word_659">die</word>
  <word id="word_660">Tourismus-Fachfrau</word>
  <word id="word_661">Felizitas</word>
  <word id="word_662">Romeiß-Stracke</word>
  <word id="word_663">.</word>
  <word id="word_664">Sie</word>
  <word id="word_665">bezeichnet</word>
  <word id="word_666">"</word>
  <word id="word_667">große</word>
  <word id="word_668">,</word>
  <word id="word_669">konzentrierte</word>
  <word id="word_670">Tourismusareale</word>
  <word id="word_671">...</word>
  <word id="word_672">,</word>
  <word id="word_673">wenn</word>
  <word id="word_674">die</word>
  <word id="word_675">Voraussetzungen</word>
  <word id="word_676">einer</word>
  <word id="word_677">sorgfältigen</word>
  <word id="word_678">Planung</word>
  <word id="word_679">und</word>
  <word id="word_680">Standortbestimmung</word>
  <word id="word_681">gegeben</word>
  <word id="word_682">sind</word>
  <word id="word_683">,</word>
  <word id="word_684">(</word>
  <word id="word_685">als</word>
  <word id="word_686">)</word>
  <word id="word_687">gerade</word>
  <word id="word_688">ökologisch</word>
  <word id="word_689">besonders</word>
  <word id="word_690">sinnvoll</word>
  <word id="word_691">"</word>
  <word id="word_692">.</word>
  <word id="word_693">Und</word>
  <word id="word_694">Freizeitexperte</word>
  <word id="word_695">H.</word>
  <word id="word_696">W.</word>
  <word id="word_697">Opaschowski</word>
  <word id="word_698">sekundiert</word>
  <word id="word_699">:</word>
  <word id="word_700">"</word>
  <word id="word_701">Ökologisch</word>
  <word id="word_702">gesehen</word>
  <word id="word_703">fast</word>
  <word id="word_704">ein</word>
  <word id="word_705">Segen</word>
  <word id="word_706">für</word>
  <word id="word_707">die</word>
  <word id="word_708">Problematik</word>
  <word id="word_709">von</word>
  <word id="word_710">Massentourismus</word>
  <word id="word_711">und</word>
  <word id="word_712">Umweltbelastung</word>
  <word id="word_713">.</word>
  <word id="word_714">"</word>
  <word id="word_715">Die</word>
  <word id="word_716">Argumente</word>
  <word id="word_717">der</word>
  <word id="word_718">Experten</word>
  <word id="word_719">sind</word>
  <word id="word_720">eindeutig</word>
  <word id="word_721">:</word>
  <word id="word_722">Die</word>
  <word id="word_723">Massen</word>
  <word id="word_724">könnten</word>
  <word id="word_725">so</word>
  <word id="word_726">kanalisiert</word>
  <word id="word_727">und</word>
  <word id="word_728">gesteuert</word>
  <word id="word_729">werden</word>
  <word id="word_730">.</word>
  <word id="word_731">Und</word>
  <word id="word_732">wo</word>
  <word id="word_733">der</word>
  <word id="word_734">begrenzte</word>
  <word id="word_735">Raum</word>
  <word id="word_736">aufs</word>
  <word id="word_737">optimalste</word>
  <word id="word_738">genutzt</word>
  <word id="word_739">wird</word>
  <word id="word_740">,</word>
  <word id="word_741">bleibe</word>
  <word id="word_742">die</word>
  <word id="word_743">Restnatur</word>
  <word id="word_744">verschont</word>
  <word id="word_745">.</word>
  <word id="word_746">Wer</word>
  <word id="word_747">so</word>
  <word id="word_748">mit</word>
  <word id="word_749">heiler</word>
  <word id="word_750">Restnatur</word>
  <word id="word_751">argumentiert</word>
  <word id="word_752">,</word>
  <word id="word_753">müßte</word>
  <word id="word_754">eigentlich</word>
  <word id="word_755">eine</word>
  <word id="word_756">Öko-Bilanz</word>
  <word id="word_757">erstellen</word>
  <word id="word_758">.</word>
  <word id="word_759">Nämlich</word>
  <word id="word_760">die</word>
  <word id="word_761">ökologischen</word>
  <word id="word_762">Kosten</word>
  <word id="word_763">abschätzen</word>
  <word id="word_764">,</word>
  <word id="word_765">die</word>
  <word id="word_766">mit</word>
  <word id="word_767">dem</word>
  <word id="word_768">Bau</word>
  <word id="word_769">und</word>
  <word id="word_770">dem</word>
  <word id="word_771">Betrieb</word>
  <word id="word_772">solcher</word>
  <word id="word_773">Großanlagen</word>
  <word id="word_774">verbunden</word>
  <word id="word_775">sind</word>
  <word id="word_776">.</word>
  <word id="word_777">Denn</word>
  <word id="word_778">jede</word>
  <word id="word_779">Großanlage</word>
  <word id="word_780">ist</word>
  <word id="word_781">von</word>
  <word id="word_782">vornherein</word>
  <word id="word_783">auf</word>
  <word id="word_784">Ressourcenverbrauch</word>
  <word id="word_785">angelegt</word>
  <word id="word_786">:</word>
  <word id="word_787">von</word>
  <word id="word_788">Landschaft</word>
  <word id="word_789">,</word>
  <word id="word_790">Energie</word>
  <word id="word_791">und</word>
  <word id="word_792">vor</word>
  <word id="word_793">allem</word>
  <word id="word_794">Wasser</word>
  <word id="word_795">.</word>
  <word id="word_796">Während</word>
  <word id="word_797">in</word>
  <word id="word_798">vielen</word>
  <word id="word_799">klassischen</word>
  <word id="word_800">Urlaubsländern</word>
  <word id="word_801">des</word>
  <word id="word_802">Südens</word>
  <word id="word_803">häufig</word>
  <word id="word_804">für</word>
  <word id="word_805">die</word>
  <word id="word_806">eigene</word>
  <word id="word_807">Bevölkerung</word>
  <word id="word_808">nicht</word>
  <word id="word_809">genügend</word>
  <word id="word_810">Wasser</word>
  <word id="word_811">zur</word>
  <word id="word_812">Verfügung</word>
  <word id="word_813">steht</word>
  <word id="word_814">,</word>
  <word id="word_815">kann</word>
  <word id="word_816">weder</word>
  <word id="word_817">dem</word>
  <word id="word_818">Edeltouristen</word>
  <word id="word_819">im</word>
  <word id="word_820">Luxushotel</word>
  <word id="word_821">das</word>
  <word id="word_822">Golfspiel</word>
  <word id="word_823">auf</word>
  <word id="word_824">gepflegtem</word>
  <word id="word_825">und</word>
  <word id="word_826">gesprengtem</word>
  <word id="word_827">Rasen</word>
  <word id="word_828">noch</word>
  <word id="word_829">dem</word>
  <word id="word_830">Pauschaltouristen</word>
  <word id="word_831">im</word>
  <word id="word_832">3-Sterne-Hotel</word>
  <word id="word_833">das</word>
  <word id="word_834">kühle</word>
  <word id="word_835">Bad</word>
  <word id="word_836">im</word>
  <word id="word_837">Swimmingpool</word>
  <word id="word_838">untersagt</word>
  <word id="word_839">werden</word>
  <word id="word_840">.</word>
  <word id="word_841">Der</word>
  <word id="word_842">augenfälligste</word>
  <word id="word_843">Eingriff</word>
  <word id="word_844">durch</word>
  <word id="word_845">den</word>
  <word id="word_846">Tourismus</word>
  <word id="word_847">ist</word>
  <word id="word_848">allerdings</word>
  <word id="word_849">in</word>
  <word id="word_850">vielen</word>
  <word id="word_851">Regionen</word>
  <word id="word_852">die</word>
  <word id="word_853">Verschandelung</word>
  <word id="word_854">der</word>
  <word id="word_855">natürlichen</word>
  <word id="word_856">Küstenlandschaften</word>
  <word id="word_857">samt</word>
  <word id="word_858">Schädigung</word>
  <word id="word_859">der</word>
  <word id="word_860">Küstengewässer</word>
  <word id="word_861">.</word>
  <word id="word_862">Noch</word>
  <word id="word_863">verstärkt</word>
  <word id="word_864">durch</word>
  <word id="word_865">die</word>
  <word id="word_866">häufig</word>
  <word id="word_867">rücksichtslose</word>
  <word id="word_868">Entsorgung</word>
  <word id="word_869">von</word>
  <word id="word_870">Müll</word>
  <word id="word_871">,</word>
  <word id="word_872">der</word>
  <word id="word_873">erst</word>
  <word id="word_874">durch</word>
  <word id="word_875">den</word>
  <word id="word_876">Tourismus</word>
  <word id="word_877">produziert</word>
  <word id="word_878">wurde</word>
  <word id="word_879">.</word>
  <word id="word_880">Der</word>
  <word id="word_881">industrielle</word>
  <word id="word_882">Abfall</word>
  <word id="word_883">wie</word>
  <word id="word_884">Konservendosen</word>
  <word id="word_885">,</word>
  <word id="word_886">Flaschen</word>
  <word id="word_887">usw.</word>
  <word id="word_888">kommt</word>
  <word id="word_889">mit</word>
  <word id="word_890">dem</word>
  <word id="word_891">Tourismus</word>
  <word id="word_892">noch</word>
  <word id="word_893">auf</word>
  <word id="word_894">die</word>
  <word id="word_895">einsamste</word>
  <word id="word_896">Insel</word>
  <word id="word_897">.</word>
  <word id="word_898">Alles</word>
  <word id="word_899">in</word>
  <word id="word_900">allem</word>
  <word id="word_901">:</word>
  <word id="word_902">ein</word>
  <word id="word_903">immenser</word>
  <word id="word_904">Landschafts-</word>
  <word id="word_905">und</word>
  <word id="word_906">Ressourcenverbrauch</word>
  <word id="word_907">,</word>
  <word id="word_908">der</word>
  <word id="word_909">in</word>
  <word id="word_910">der</word>
  <word id="word_911">Regel</word>
  <word id="word_912">nie</word>
  <word id="word_913">thematisiert</word>
  <word id="word_914">wird</word>
  <word id="word_915">.</word>
  <word id="word_916">Darüber</word>
  <word id="word_917">hinaus</word>
  <word id="word_918">braucht</word>
  <word id="word_919">die</word>
  <word id="word_920">touristische</word>
  <word id="word_921">Großanlage</word>
  <word id="word_922">vor</word>
  <word id="word_923">allem</word>
  <word id="word_924">eines</word>
  <word id="word_925">:</word>
  <word id="word_926">eine</word>
  <word id="word_927">immense</word>
  <word id="word_928">Ausstattung</word>
  <word id="word_929">.</word>
  <word id="word_930">Die</word>
  <word id="word_931">Touristen</word>
  <word id="word_932">wollen</word>
  <word id="word_933">ihren</word>
  <word id="word_934">gewohnten</word>
  <word id="word_935">Luxus</word>
  <word id="word_936">.</word>
  <word id="word_937">Vom</word>
  <word id="word_938">Champagner</word>
  <word id="word_939">bis</word>
  <word id="word_940">zur</word>
  <word id="word_941">Klimaanlage</word>
  <word id="word_942">.</word>
  <word id="word_943">Die</word>
  <word id="word_944">meisten</word>
  <word id="word_945">dieser</word>
  <word id="word_946">Güter</word>
  <word id="word_947">müssen</word>
  <word id="word_948">importiert</word>
  <word id="word_949">werden</word>
  <word id="word_950">.</word>
  <word id="word_951">Importiert</word>
  <word id="word_952">werden</word>
  <word id="word_953">auch</word>
  <word id="word_954">die</word>
  <word id="word_955">Touristen</word>
  <word id="word_956">selbst</word>
  <word id="word_957">.</word>
  <word id="word_958">Der</word>
  <word id="word_959">Transport</word>
  <word id="word_960">via</word>
  <word id="word_961">Flugzeug</word>
  <word id="word_962">ist</word>
  <word id="word_963">der</word>
  <word id="word_964">größte</word>
  <word id="word_965">Ressourcenfresser</word>
  <word id="word_966">und</word>
  <word id="word_967">Klimakiller</word>
  <word id="word_968">.</word>
  <word id="word_969">Schon</word>
  <word id="word_970">jetzt</word>
  <word id="word_971">verursacht</word>
  <word id="word_972">der</word>
  <word id="word_973">internationale</word>
  <word id="word_974">Flugverkehr</word>
  <word id="word_975">zu</word>
  <word id="word_976">etwa</word>
  <word id="word_977">5</word>
  <word id="word_978">Prozent</word>
  <word id="word_979">den</word>
  <word id="word_980">Treibhauseffekt</word>
  <word id="word_981">.</word>
  <word id="word_982">Doch</word>
  <word id="word_983">erst</word>
  <word id="word_984">ca.</word>
  <word id="word_985">5</word>
  <word id="word_986">Prozent</word>
  <word id="word_987">der</word>
  <word id="word_988">Menschheit</word>
  <word id="word_989">auf</word>
  <word id="word_990">diesem</word>
  <word id="word_991">Globus</word>
  <word id="word_992">fliegen</word>
  <word id="word_993">!</word>
  <word id="word_994">Tendenz</word>
  <word id="word_995">steigend</word>
  <word id="word_996">:</word>
  <word id="word_997">Allein</word>
  <word id="word_998">in</word>
  <word id="word_999">der</word>
  <word id="word_1000">Bundesrepublik</word>
  <word id="word_1001">liegt</word>
  <word id="word_1002">die</word>
  <word id="word_1003">derzeitige</word>
  <word id="word_1004">Zuwachsrate</word>
  <word id="word_1005">bei</word>
  <word id="word_1006">jährlich</word>
  <word id="word_1007">7</word>
  <word id="word_1008">Prozent</word>
  <word id="word_1009">.</word>
  <word id="word_1010">Hierzulande</word>
  <word id="word_1011">macht</word>
  <word id="word_1012">der</word>
  <word id="word_1013">Flugverkehr</word>
  <word id="word_1014">bereits</word>
  <word id="word_1015">30</word>
  <word id="word_1016">Prozent</word>
  <word id="word_1017">der</word>
  <word id="word_1018">verkehrlichen</word>
  <word id="word_1019">Gesamtbelastung</word>
  <word id="word_1020">aus</word>
  <word id="word_1021">,</word>
  <word id="word_1022">so</word>
  <word id="word_1023">die</word>
  <word id="word_1024">Berechnung</word>
  <word id="word_1025">Wuppertaler</word>
  <word id="word_1026">Klimaexperten</word>
  <word id="word_1027">.</word>
  <word id="word_1028">Ohne</word>
  <word id="word_1029">den</word>
  <word id="word_1030">günstigen</word>
  <word id="word_1031">Charterflug</word>
  <word id="word_1032">nach</word>
  <word id="word_1033">Kenia</word>
  <word id="word_1034">wäre</word>
  <word id="word_1035">die</word>
  <word id="word_1036">dortige</word>
  <word id="word_1037">Großanlage</word>
  <word id="word_1038">nicht</word>
  <word id="word_1039">rentabel</word>
  <word id="word_1040">.</word>
  <word id="word_1041">Das</word>
  <word id="word_1042">heißt</word>
  <word id="word_1043">:</word>
  <word id="word_1044">ohne</word>
  <word id="word_1045">Flugverkehr</word>
  <word id="word_1046">kein</word>
  <word id="word_1047">expandierender</word>
  <word id="word_1048">Tourismus</word>
  <word id="word_1049">.</word>
  <word id="word_1050">Und</word>
  <word id="word_1051">umgekehrt</word>
  <word id="word_1052">:</word>
  <word id="word_1053">ohne</word>
  <word id="word_1054">Großanlagen</word>
  <word id="word_1055">und</word>
  <word id="word_1056">eine</word>
  <word id="word_1057">touristische</word>
  <word id="word_1058">Infrastruktur</word>
  <word id="word_1059">wären</word>
  <word id="word_1060">Thailand</word>
  <word id="word_1061">oder</word>
  <word id="word_1062">die</word>
  <word id="word_1063">Dominikanische</word>
  <word id="word_1064">Republik</word>
  <word id="word_1065">kein</word>
  <word id="word_1066">massenhaftes</word>
  <word id="word_1067">Charterflugziel</word>
  <word id="word_1068">.</word>
  <word id="word_1069">Erst</word>
  <word id="word_1070">die</word>
  <word id="word_1071">touristische</word>
  <word id="word_1072">Infrastruktur</word>
  <word id="word_1073">schafft</word>
  <word id="word_1074">eine</word>
  <word id="word_1075">gesteigerte</word>
  <word id="word_1076">Nachfrage</word>
  <word id="word_1077">,</word>
  <word id="word_1078">den</word>
  <word id="word_1079">vielgeschmähten</word>
  <word id="word_1080">Massentourismus</word>
  <word id="word_1081">.</word>
  <word id="word_1082">Lediglich</word>
  <word id="word_1083">innen</word>
  <word id="word_1084">,</word>
  <word id="word_1085">in</word>
  <word id="word_1086">der</word>
  <word id="word_1087">Anlage</word>
  <word id="word_1088">,</word>
  <word id="word_1089">geht</word>
  <word id="word_1090">es</word>
  <word id="word_1091">"</word>
  <word id="word_1092">clean</word>
  <word id="word_1093">"</word>
  <word id="word_1094">zu</word>
  <word id="word_1095">.</word>
  <word id="word_1096">Zumindest</word>
  <word id="word_1097">bei</word>
  <word id="word_1098">progressiven</word>
  <word id="word_1099">Veranstaltern</word>
  <word id="word_1100">herrscht</word>
  <word id="word_1101">eherne</word>
  <word id="word_1102">Ökomoral</word>
  <word id="word_1103">:</word>
  <word id="word_1104">Handtücher</word>
  <word id="word_1105">werden</word>
  <word id="word_1106">nicht</word>
  <word id="word_1107">mehr</word>
  <word id="word_1108">täglich</word>
  <word id="word_1109">gewechselt</word>
  <word id="word_1110">,</word>
  <word id="word_1111">Prospekte</word>
  <word id="word_1112">werden</word>
  <word id="word_1113">auf</word>
  <word id="word_1114">Recyclingpapier</word>
  <word id="word_1115">gedruckt</word>
  <word id="word_1116">,</word>
  <word id="word_1117">keine</word>
  <word id="word_1118">Klospülung</word>
  <word id="word_1119">ohne</word>
  <word id="word_1120">Wasserstopper</word>
  <word id="word_1121">...</word>
  <word id="word_1122">Doch</word>
  <word id="word_1123">sollte</word>
  <word id="word_1124">sich</word>
  <word id="word_1125">je</word>
  <word id="word_1126">der</word>
  <word id="word_1127">Publikumsgeschmack</word>
  <word id="word_1128">an</word>
  <word id="word_1129">diesen</word>
  <word id="word_1130">Anlagen</word>
  <word id="word_1131">verflüchtigen</word>
  <word id="word_1132">,</word>
  <word id="word_1133">sollte</word>
  <word id="word_1134">Neues</word>
  <word id="word_1135">gefragt</word>
  <word id="word_1136">sein</word>
  <word id="word_1137">,</word>
  <word id="word_1138">dann</word>
  <word id="word_1139">werden</word>
  <word id="word_1140">riesige</word>
  <word id="word_1141">Müllhalden</word>
  <word id="word_1142">zurückbleiben</word>
  <word id="word_1143">,</word>
  <word id="word_1144">an</word>
  <word id="word_1145">denen</word>
  <word id="word_1146">sich</word>
  <word id="word_1147">der</word>
  <word id="word_1148">Zahn</word>
  <word id="word_1149">der</word>
  <word id="word_1150">Zeit</word>
  <word id="word_1151">stumpf</word>
  <word id="word_1152">nagen</word>
  <word id="word_1153">wird</word>
  <word id="word_1154">.</word>
  <word id="word_1155">Wie</word>
  <word id="word_1156">also</word>
  <word id="word_1157">schützen</word>
  <word id="word_1158">Ghettos</word>
  <word id="word_1159">die</word>
  <word id="word_1160">Natur</word>
  <word id="word_1161">?</word>
  <word id="word_1162">Global</word>
  <word id="word_1163">gesehen</word>
  <word id="word_1164">-</word>
  <word id="word_1165">gar</word>
  <word id="word_1166">nicht</word>
  <word id="word_1167">.</word>
  <word id="word_1168">Als</word>
  <word id="word_1169">ökologisch</word>
  <word id="word_1170">wird</word>
  <word id="word_1171">hier</word>
  <word id="word_1172">lediglich</word>
  <word id="word_1173">verstanden</word>
  <word id="word_1174">:</word>
  <word id="word_1175">reibungsloses</word>
  <word id="word_1176">Massenmanagement</word>
  <word id="word_1177">.</word>
  <word id="word_1178">Die</word>
  <word id="word_1179">durch</word>
  <word id="word_1180">und</word>
  <word id="word_1181">durch</word>
  <word id="word_1182">ökonomische</word>
  <word id="word_1183">Logik</word>
  <word id="word_1184">wird</word>
  <word id="word_1185">im</word>
  <word id="word_1186">nachhinein</word>
  <word id="word_1187">mit</word>
  <word id="word_1188">ökologischen</word>
  <word id="word_1189">Argumenten</word>
  <word id="word_1190">aufgewertet</word>
  <word id="word_1191">.</word>
  <word id="word_1192">Sind</word>
  <word id="word_1193">soziale</word>
  <word id="word_1194">Kontakte</word>
  <word id="word_1195">schädlich</word>
  <word id="word_1196">?</word>
  <word id="word_1197">Nichtsdestotrotz</word>
  <word id="word_1198">:</word>
  <word id="word_1199">Bei</word>
  <word id="word_1200">der</word>
  <word id="word_1201">Suche</word>
  <word id="word_1202">nach</word>
  <word id="word_1203">umwelt-</word>
  <word id="word_1204">und</word>
  <word id="word_1205">sozialverträglichen</word>
  <word id="word_1206">Reiseformen</word>
  <word id="word_1207">wird</word>
  <word id="word_1208">die</word>
  <word id="word_1209">Großanlage</word>
  <word id="word_1210">favorisiert</word>
  <word id="word_1211">-</word>
  <word id="word_1212">auch</word>
  <word id="word_1213">unter</word>
  <word id="word_1214">sozialen</word>
  <word id="word_1215">Aspekten</word>
  <word id="word_1216">.</word>
  <word id="word_1217">Was</word>
  <word id="word_1218">aber</word>
  <word id="word_1219">ist</word>
  <word id="word_1220">eigentlich</word>
  <word id="word_1221">gegen</word>
  <word id="word_1222">eine</word>
  <word id="word_1223">touristische</word>
  <word id="word_1224">Vielfalt</word>
  <word id="word_1225">mit</word>
  <word id="word_1226">einer</word>
  <word id="word_1227">mittelständischen</word>
  <word id="word_1228">Infrastruktur</word>
  <word id="word_1229">und</word>
  <word id="word_1230">kleinen</word>
  <word id="word_1231">Pensionen</word>
  <word id="word_1232">wie</word>
  <word id="word_1233">auf</word>
  <word id="word_1234">Kreta</word>
  <word id="word_1235">oder</word>
  <word id="word_1236">Gomera</word>
  <word id="word_1237">einzuwenden</word>
  <word id="word_1238">?</word>
  <word id="word_1239">Warum</word>
  <word id="word_1240">muß</word>
  <word id="word_1241">der</word>
  <word id="word_1242">Großtourismus</word>
  <word id="word_1243">favorisiert</word>
  <word id="word_1244">werden</word>
  <word id="word_1245">?</word>
  <word id="word_1246">Weil</word>
  <word id="word_1247">dieser</word>
  <word id="word_1248">als</word>
  <word id="word_1249">Wachstumsindustrie</word>
  <word id="word_1250">den</word>
  <word id="word_1251">Marktgesetzen</word>
  <word id="word_1252">so</word>
  <word id="word_1253">mustergültig</word>
  <word id="word_1254">entspricht</word>
  <word id="word_1255">?</word>
  <word id="word_1256">Mit</word>
  <word id="word_1257">dem</word>
  <word id="word_1258">Argument</word>
  <word id="word_1259">,</word>
  <word id="word_1260">daß</word>
  <word id="word_1261">geschlossene</word>
  <word id="word_1262">Anlagen</word>
  <word id="word_1263">die</word>
  <word id="word_1264">Bereisten</word>
  <word id="word_1265">"</word>
  <word id="word_1266">vor</word>
  <word id="word_1267">übergreifender</word>
  <word id="word_1268">ökologischer</word>
  <word id="word_1269">und</word>
  <word id="word_1270">vor</word>
  <word id="word_1271">allem</word>
  <word id="word_1272">geistig-kultureller</word>
  <word id="word_1273">Infektion</word>
  <word id="word_1274">"</word>
  <word id="word_1275">schützen</word>
  <word id="word_1276">,</word>
  <word id="word_1277">nehmen</word>
  <word id="word_1278">selbst</word>
  <word id="word_1279">Tourismuskritiker</word>
  <word id="word_1280">wie</word>
  <word id="word_1281">Jost</word>
  <word id="word_1282">Krippendorf</word>
  <word id="word_1283">,</word>
  <word id="word_1284">Apologet</word>
  <word id="word_1285">eines</word>
  <word id="word_1286">sanften</word>
  <word id="word_1287">Tourismus</word>
  <word id="word_1288">,</word>
  <word id="word_1289">allen</word>
  <word id="word_1290">weiteren</word>
  <word id="word_1291">Einwänden</word>
  <word id="word_1292">gegen</word>
  <word id="word_1293">das</word>
  <word id="word_1294">touristische</word>
  <word id="word_1295">Ghetto</word>
  <word id="word_1296">den</word>
  <word id="word_1297">Wind</word>
  <word id="word_1298">aus</word>
  <word id="word_1299">den</word>
  <word id="word_1300">Segeln</word>
  <word id="word_1301">.</word>
  <word id="word_1302">Offenbar</word>
  <word id="word_1303">sind</word>
  <word id="word_1304">soziale</word>
  <word id="word_1305">Kontakte</word>
  <word id="word_1306">schädlich</word>
  <word id="word_1307">und</word>
  <word id="word_1308">infektiös</word>
  <word id="word_1309">bedrohlich</word>
  <word id="word_1310">wie</word>
  <word id="word_1311">Aids</word>
  <word id="word_1312">.</word>
  <word id="word_1313">Wer</word>
  <word id="word_1314">soll</word>
  <word id="word_1315">hier</word>
  <word id="word_1316">eigentlich</word>
  <word id="word_1317">vor</word>
  <word id="word_1318">wem</word>
  <word id="word_1319">geschützt</word>
  <word id="word_1320">werden</word>
  <word id="word_1321">?</word>
  <word id="word_1322">Etwa</word>
  <word id="word_1323">der</word>
  <word id="word_1324">Einheimische</word>
  <word id="word_1325">vor</word>
  <word id="word_1326">deutschem</word>
  <word id="word_1327">Bier</word>
  <word id="word_1328">?</word>
  <word id="word_1329">Oder</word>
  <word id="word_1330">den</word>
  <word id="word_1331">Begehrlichkeiten</word>
  <word id="word_1332">einer</word>
  <word id="word_1333">Freizeitgesellschaft</word>
  <word id="word_1334">?</word>
  <word id="word_1335">Vor</word>
  <word id="word_1336">Luxusgütern</word>
  <word id="word_1337">,</word>
  <word id="word_1338">die</word>
  <word id="word_1339">nur</word>
  <word id="word_1340">einem</word>
  <word id="word_1341">kleinen</word>
  <word id="word_1342">Teil</word>
  <word id="word_1343">der</word>
  <word id="word_1344">Welt</word>
  <word id="word_1345">vorbehalten</word>
  <word id="word_1346">sind</word>
  <word id="word_1347">?</word>
  <word id="word_1348">In</word>
  <word id="word_1349">einem</word>
  <word id="word_1350">Punkt</word>
  <word id="word_1351">hat</word>
  <word id="word_1352">Krippendorf</word>
  <word id="word_1353">sicherlich</word>
  <word id="word_1354">recht</word>
  <word id="word_1355">:</word>
  <word id="word_1356">Kultureller</word>
  <word id="word_1357">Austausch</word>
  <word id="word_1358">,</word>
  <word id="word_1359">der</word>
  <word id="word_1360">eigentlich</word>
  <word id="word_1361">der</word>
  <word id="word_1362">Maßstab</word>
  <word id="word_1363">für</word>
  <word id="word_1364">sozialverträgliches</word>
  <word id="word_1365">Reisen</word>
  <word id="word_1366">sein</word>
  <word id="word_1367">sollte</word>
  <word id="word_1368">,</word>
  <word id="word_1369">findet</word>
  <word id="word_1370">hier</word>
  <word id="word_1371">nicht</word>
  <word id="word_1372">mehr</word>
  <word id="word_1373">statt</word>
  <word id="word_1374">.</word>
  <word id="word_1375">Die</word>
  <word id="word_1376">Großanlage</word>
  <word id="word_1377">oder</word>
  <word id="word_1378">der</word>
  <word id="word_1379">Club</word>
  <word id="word_1380">haben</word>
  <word id="word_1381">mit</word>
  <word id="word_1382">ihrem</word>
  <word id="word_1383">auf</word>
  <word id="word_1384">Urlaub</word>
  <word id="word_1385">eingestellten</word>
  <word id="word_1386">standardisierten</word>
  <word id="word_1387">Eigenleben</word>
  <word id="word_1388">nichts</word>
  <word id="word_1389">mit</word>
  <word id="word_1390">dem</word>
  <word id="word_1391">Alltag</word>
  <word id="word_1392">der</word>
  <word id="word_1393">Bevölkerung</word>
  <word id="word_1394">eines</word>
  <word id="word_1395">besuchten</word>
  <word id="word_1396">Landes</word>
  <word id="word_1397">gemein</word>
  <word id="word_1398">.</word>
  <word id="word_1399">Die</word>
  <word id="word_1400">Touristen</word>
  <word id="word_1401">dort</word>
  <word id="word_1402">treten</word>
  <word id="word_1403">den</word>
  <word id="word_1404">Einheimischen</word>
  <word id="word_1405">nicht</word>
  <word id="word_1406">mehr</word>
  <word id="word_1407">auf</word>
  <word id="word_1408">die</word>
  <word id="word_1409">Füße</word>
  <word id="word_1410">.</word>
  <word id="word_1411">Sie</word>
  <word id="word_1412">lassen</word>
  <word id="word_1413">sie</word>
  <word id="word_1414">allenfalls</word>
  <word id="word_1415">für</word>
  <word id="word_1416">sich</word>
  <word id="word_1417">laufen</word>
  <word id="word_1418">,</word>
  <word id="word_1419">singen</word>
  <word id="word_1420">,</word>
  <word id="word_1421">spielen</word>
  <word id="word_1422">und</word>
  <word id="word_1423">tanzen</word>
  <word id="word_1424">.</word>
  <word id="word_1425">Man</word>
  <word id="word_1426">bleibt</word>
  <word id="word_1427">unter</word>
  <word id="word_1428">sich</word>
  <word id="word_1429">,</word>
  <word id="word_1430">abgeschottet</word>
  <word id="word_1431">von</word>
  <word id="word_1432">den</word>
  <word id="word_1433">Menschen</word>
  <word id="word_1434">,</word>
  <word id="word_1435">und</word>
  <word id="word_1436">urlaubt</word>
  <word id="word_1437">im</word>
  <word id="word_1438">eigenen</word>
  <word id="word_1439">Witz</word>
  <word id="word_1440">spaßig</word>
  <word id="word_1441">vor</word>
  <word id="word_1442">sich</word>
  <word id="word_1443">hin</word>
  <word id="word_1444">.</word>
  <word id="word_1445">Die</word>
  <word id="word_1446">schützenden</word>
  <word id="word_1447">Ghettos</word>
  <word id="word_1448">schützen</word>
  <word id="word_1449">denn</word>
  <word id="word_1450">auch</word>
  <word id="word_1451">weniger</word>
  <word id="word_1452">die</word>
  <word id="word_1453">ungefragt</word>
  <word id="word_1454">heimgesuchten</word>
  <word id="word_1455">Gastgeber</word>
  <word id="word_1456">als</word>
  <word id="word_1457">die</word>
  <word id="word_1458">Touristen</word>
  <word id="word_1459">.</word>
  <word id="word_1460">Die</word>
  <word id="word_1461">verschiedenen</word>
  <word id="word_1462">aufeinandertreffenden</word>
  <word id="word_1463">Kulturelemente</word>
  <word id="word_1464">werden</word>
  <word id="word_1465">vorsorglich</word>
  <word id="word_1466">voneinander</word>
  <word id="word_1467">isoliert</word>
  <word id="word_1468">.</word>
  <word id="word_1469">Man</word>
  <word id="word_1470">nimmt</word>
  <word id="word_1471">sich</word>
  <word id="word_1472">allenfalls</word>
  <word id="word_1473">,</word>
  <word id="word_1474">was</word>
  <word id="word_1475">man</word>
  <word id="word_1476">braucht</word>
  <word id="word_1477">für</word>
  <word id="word_1478">die</word>
  <word id="word_1479">heile</word>
  <word id="word_1480">Urlaubswelt</word>
  <word id="word_1481">,</word>
  <word id="word_1482">und</word>
  <word id="word_1483">läßt</word>
  <word id="word_1484">die</word>
  <word id="word_1485">vielschichtige</word>
  <word id="word_1486">Realität</word>
  <word id="word_1487">draußen</word>
  <word id="word_1488">vor</word>
  <word id="word_1489">der</word>
  <word id="word_1490">Anlage</word>
  <word id="word_1491">.</word>
  <word id="word_1492">Sie</word>
  <word id="word_1493">ist</word>
  <word id="word_1494">ein</word>
  <word id="word_1495">luxuriöser</word>
  <word id="word_1496">Fremdkörper</word>
  <word id="word_1497">.</word>
  <word id="word_1498">So</word>
  <word id="word_1499">abgeschlossen</word>
  <word id="word_1500">sie</word>
  <word id="word_1501">ist</word>
  <word id="word_1502">,</word>
  <word id="word_1503">so</word>
  <word id="word_1504">neugierig</word>
  <word id="word_1505">macht</word>
  <word id="word_1506">sie</word>
  <word id="word_1507">auch</word>
  <word id="word_1508">.</word>
  <word id="word_1509">Sie</word>
  <word id="word_1510">weckt</word>
  <word id="word_1511">in</word>
  <word id="word_1512">der</word>
  <word id="word_1513">Tat</word>
  <word id="word_1514">Begehrlichkeiten</word>
  <word id="word_1515">,</word>
  <word id="word_1516">denn</word>
  <word id="word_1517">sie</word>
  <word id="word_1518">demonstriert</word>
  <word id="word_1519">einen</word>
  <word id="word_1520">attraktiven</word>
  <word id="word_1521">Lebensstil</word>
  <word id="word_1522">:</word>
  <word id="word_1523">Geld</word>
  <word id="word_1524">,</word>
  <word id="word_1525">Müßiggang</word>
  <word id="word_1526">,</word>
  <word id="word_1527">Genuß</word>
  <word id="word_1528">...</word>
  <word id="word_1529">Das</word>
  <word id="word_1530">unwiderstehliche</word>
  <word id="word_1531">Flair</word>
  <word id="word_1532">der</word>
  <word id="word_1533">großen</word>
  <word id="word_1534">weiten</word>
  <word id="word_1535">satten</word>
  <word id="word_1536">Welt</word>
  <word id="word_1537">.</word>
  <word id="word_1538">So</word>
  <word id="word_1539">propagandistisch</word>
  <word id="word_1540">wie</word>
  <word id="word_1541">die</word>
  <word id="word_1542">internationalen</word>
  <word id="word_1543">Werbekampagnen</word>
  <word id="word_1544">von</word>
  <word id="word_1545">Coca-Cola</word>
  <word id="word_1546">,</word>
  <word id="word_1547">Nike</word>
  <word id="word_1548">,</word>
  <word id="word_1549">Levi's</word>
  <word id="word_1550">und</word>
  <word id="word_1551">den</word>
  <word id="word_1552">anderen</word>
  <word id="word_1553">Botschaftern</word>
  <word id="word_1554">der</word>
  <word id="word_1555">Konsumgesellschaften</word>
  <word id="word_1556">.</word>
  <word id="word_1557">Auch</word>
  <word id="word_1558">Tourismus</word>
  <word id="word_1559">bringt</word>
  <word id="word_1560">westlichen</word>
  <word id="word_1561">Lebensstil</word>
  <word id="word_1562">.</word>
  <word id="word_1563">Doch</word>
  <word id="word_1564">in</word>
  <word id="word_1565">seiner</word>
  <word id="word_1566">industriellen</word>
  <word id="word_1567">Form</word>
  <word id="word_1568">berührt</word>
  <word id="word_1569">er</word>
  <word id="word_1570">direkt</word>
  <word id="word_1571">die</word>
  <word id="word_1572">Lebensgrundlagen</word>
  <word id="word_1573">der</word>
  <word id="word_1574">Bevölkerung</word>
  <word id="word_1575">.</word>
  <word id="word_1576">Des</word>
  <word id="word_1577">Bauern</word>
  <word id="word_1578">,</word>
  <word id="word_1579">der</word>
  <word id="word_1580">auf</word>
  <word id="word_1581">Land</word>
  <word id="word_1582">verzichten</word>
  <word id="word_1583">muß</word>
  <word id="word_1584">-</word>
  <word id="word_1585">nicht</word>
  <word id="word_1586">selten</word>
  <word id="word_1587">sogar</word>
  <word id="word_1588">zwangsumgesiedelt</word>
  <word id="word_1589">wird</word>
  <word id="word_1590">-</word>
  <word id="word_1591">,</word>
  <word id="word_1592">oder</word>
  <word id="word_1593">des</word>
  <word id="word_1594">Fischers</word>
  <word id="word_1595">,</word>
  <word id="word_1596">der</word>
  <word id="word_1597">seine</word>
  <word id="word_1598">angestammten</word>
  <word id="word_1599">Fanggründe</word>
  <word id="word_1600">verliert</word>
  <word id="word_1601">.</word>
  <word id="word_1602">Der</word>
  <word id="word_1603">Einheimische</word>
  <word id="word_1604">kann</word>
  <word id="word_1605">,</word>
  <word id="word_1606">wenn</word>
  <word id="word_1607">er</word>
  <word id="word_1608">Glück</word>
  <word id="word_1609">hat</word>
  <word id="word_1610">,</word>
  <word id="word_1611">als</word>
  <word id="word_1612">Barbesitzer</word>
  <word id="word_1613">durch</word>
  <word id="word_1614">die</word>
  <word id="word_1615">Touristen</word>
  <word id="word_1616">besser</word>
  <word id="word_1617">leben</word>
  <word id="word_1618">.</word>
  <word id="word_1619">Wenn</word>
  <word id="word_1620">er</word>
  <word id="word_1621">Pech</word>
  <word id="word_1622">hat</word>
  <word id="word_1623">,</word>
  <word id="word_1624">verschlechtert</word>
  <word id="word_1625">sich</word>
  <word id="word_1626">seine</word>
  <word id="word_1627">Misere</word>
  <word id="word_1628">noch</word>
  <word id="word_1629">als</word>
  <word id="word_1630">unterbezahlter</word>
  <word id="word_1631">Kellner</word>
  <word id="word_1632">im</word>
  <word id="word_1633">Strandhotel</word>
  <word id="word_1634">.</word>
  <word id="word_1635">Viele</word>
  <word id="word_1636">wählen</word>
  <word id="word_1637">gleich</word>
  <word id="word_1638">den</word>
  <word id="word_1639">Weg</word>
  <word id="word_1640">in</word>
  <word id="word_1641">die</word>
  <word id="word_1642">Prostitution</word>
  <word id="word_1643">.</word>
  <word id="word_1644">Eine</word>
  <word id="word_1645">Rückkehr</word>
  <word id="word_1646">zu</word>
  <word id="word_1647">den</word>
  <word id="word_1648">traditionellen</word>
  <word id="word_1649">Strukturen</word>
  <word id="word_1650">ist</word>
  <word id="word_1651">ohnehin</word>
  <word id="word_1652">nicht</word>
  <word id="word_1653">möglich</word>
  <word id="word_1654">.</word>
  <word id="word_1655">Die</word>
  <word id="word_1656">Einheimischen</word>
  <word id="word_1657">müssen</word>
  <word id="word_1658">sich</word>
  <word id="word_1659">,</word>
  <word id="word_1660">ob</word>
  <word id="word_1661">sie</word>
  <word id="word_1662">wollen</word>
  <word id="word_1663">oder</word>
  <word id="word_1664">nicht</word>
  <word id="word_1665">,</word>
  <word id="word_1666">den</word>
  <word id="word_1667">neuen</word>
  <word id="word_1668">Bedingungen</word>
  <word id="word_1669">aus</word>
  <word id="word_1670">ökonomischer</word>
  <word id="word_1671">Abhängigkeit</word>
  <word id="word_1672">beugen</word>
  <word id="word_1673">.</word>
  <word id="word_1674">Großtourismus</word>
  <word id="word_1675">schafft</word>
  <word id="word_1676">keine</word>
  <word id="word_1677">tragfähigen</word>
  <word id="word_1678">,</word>
  <word id="word_1679">eigenständigen</word>
  <word id="word_1680">wirtschaftlichen</word>
  <word id="word_1681">Strukturen</word>
  <word id="word_1682">.</word>
  <word id="word_1683">Im</word>
  <word id="word_1684">Gegenteil</word>
  <word id="word_1685">:</word>
  <word id="word_1686">Er</word>
  <word id="word_1687">verfestigt</word>
  <word id="word_1688">internationale</word>
  <word id="word_1689">Abhängigkeiten</word>
  <word id="word_1690">.</word>
  <word id="word_1691">Mag</word>
  <word id="word_1692">er</word>
  <word id="word_1693">auch</word>
  <word id="word_1694">zur</word>
  <word id="word_1695">Schuldenrückzahlung</word>
  <word id="word_1696">und</word>
  <word id="word_1697">damit</word>
  <word id="word_1698">zum</word>
  <word id="word_1699">Erhalt</word>
  <word id="word_1700">weiterer</word>
  <word id="word_1701">Kredite</word>
  <word id="word_1702">nützlich</word>
  <word id="word_1703">sein</word>
  <word id="word_1704">,</word>
  <word id="word_1705">eigenständige</word>
  <word id="word_1706">ökonomische</word>
  <word id="word_1707">Möglichkeiten</word>
  <word id="word_1708">fördert</word>
  <word id="word_1709">er</word>
  <word id="word_1710">-</word>
  <word id="word_1711">wenn</word>
  <word id="word_1712">überhaupt</word>
  <word id="word_1713">-</word>
  <word id="word_1714">nur</word>
  <word id="word_1715">am</word>
  <word id="word_1716">Rande</word>
  <word id="word_1717">.</word>
  <word id="word_1718">Denn</word>
  <word id="word_1719">die</word>
  <word id="word_1720">zur</word>
  <word id="word_1721">Eigenkapitalbildung</word>
  <word id="word_1722">dringend</word>
  <word id="word_1723">benötigten</word>
  <word id="word_1724">Devisen</word>
  <word id="word_1725">fließen</word>
  <word id="word_1726">wieder</word>
  <word id="word_1727">ab</word>
  <word id="word_1728">.</word>
  <word id="word_1729">Letztendlich</word>
  <word id="word_1730">wirtschaftet</word>
  <word id="word_1731">der</word>
  <word id="word_1732">vielgerühmte</word>
  <word id="word_1733">Devisenbringer</word>
  <word id="word_1734">in</word>
  <word id="word_1735">die</word>
  <word id="word_1736">eigene</word>
  <word id="word_1737">Tasche</word>
  <word id="word_1738">.</word>
  <word id="word_1739">Ist</word>
  <word id="word_1740">dies</word>
  <word id="word_1741">sozial</word>
  <word id="word_1742">verantwortlich</word>
  <word id="word_1743">im</word>
  <word id="word_1744">Sinne</word>
  <word id="word_1745">der</word>
  <word id="word_1746">Gastgeber</word>
  <word id="word_1747">?</word>
  <word id="word_1748">Die</word>
  <word id="word_1749">Einrichtung</word>
  <word id="word_1750">ist</word>
  <word id="word_1751">eine</word>
  <word id="word_1752">omnipotente</word>
  <word id="word_1753">Mama</word>
  <word id="word_1754">Aber</word>
  <word id="word_1755">schließlich</word>
  <word id="word_1756">will</word>
  <word id="word_1757">der</word>
  <word id="word_1758">Tourismus</word>
  <word id="word_1759">nicht</word>
  <word id="word_1760">die</word>
  <word id="word_1761">letzten</word>
  <word id="word_1762">Paradiese</word>
  <word id="word_1763">dieser</word>
  <word id="word_1764">Erde</word>
  <word id="word_1765">befrieden</word>
  <word id="word_1766">,</word>
  <word id="word_1767">sondern</word>
  <word id="word_1768">sie</word>
  <word id="word_1769">erschließen</word>
  <word id="word_1770">-</word>
  <word id="word_1771">für</word>
  <word id="word_1772">den</word>
  <word id="word_1773">Touristen</word>
  <word id="word_1774">.</word>
  <word id="word_1775">Er</word>
  <word id="word_1776">soll</word>
  <word id="word_1777">Gefallen</word>
  <word id="word_1778">daran</word>
  <word id="word_1779">finden</word>
  <word id="word_1780">.</word>
  <word id="word_1781">Freizeitforscher</word>
  <word id="word_1782">H.</word>
  <word id="word_1783">W.</word>
  <word id="word_1784">Opaschowski</word>
  <word id="word_1785">hat</word>
  <word id="word_1786">einen</word>
  <word id="word_1787">Kriterienkatalog</word>
  <word id="word_1788">für</word>
  <word id="word_1789">Glücksangebote</word>
  <word id="word_1790">entwickelt</word>
  <word id="word_1791">:</word>
  <word id="word_1792">"</word>
  <word id="word_1793">der</word>
  <word id="word_1794">schöne</word>
  <word id="word_1795">Augenblick</word>
  <word id="word_1796">,</word>
  <word id="word_1797">die</word>
  <word id="word_1798">völlige</word>
  <word id="word_1799">Entspannung</word>
  <word id="word_1800">,</word>
  <word id="word_1801">die</word>
  <word id="word_1802">absolute</word>
  <word id="word_1803">Geborgenheit</word>
  <word id="word_1804">,</word>
  <word id="word_1805">die</word>
  <word id="word_1806">vollkommene</word>
  <word id="word_1807">Harmonie</word>
  <word id="word_1808">,</word>
  <word id="word_1809">die</word>
  <word id="word_1810">angenehme</word>
  <word id="word_1811">Atmosphäre</word>
  <word id="word_1812">,</word>
  <word id="word_1813">die</word>
  <word id="word_1814">ausgelassene</word>
  <word id="word_1815">Stimmung</word>
  <word id="word_1816">,</word>
  <word id="word_1817">das</word>
  <word id="word_1818">außergewöhnliche</word>
  <word id="word_1819">Ereignis</word>
  <word id="word_1820">,</word>
  <word id="word_1821">das</word>
  <word id="word_1822">grenzenlose</word>
  <word id="word_1823">Freiheitsgefühl</word>
  <word id="word_1824">,</word>
  <word id="word_1825">die</word>
  <word id="word_1826">perfekte</word>
  <word id="word_1827">Illusion</word>
  <word id="word_1828">,</word>
  <word id="word_1829">der</word>
  <word id="word_1830">letzte</word>
  <word id="word_1831">Kick</word>
  <word id="word_1832">"</word>
  <word id="word_1833">.</word>
  <word id="word_1834">Schlicht</word>
  <word id="word_1835">alles</word>
  <word id="word_1836">,</word>
  <word id="word_1837">was</word>
  <word id="word_1838">wir</word>
  <word id="word_1839">mögen</word>
  <word id="word_1840">,</word>
  <word id="word_1841">wird</word>
  <word id="word_1842">in</word>
  <word id="word_1843">Gefühlsszenarien</word>
  <word id="word_1844">übersetzt</word>
  <word id="word_1845">.</word>
  <word id="word_1846">Touristische</word>
  <word id="word_1847">Experten</word>
  <word id="word_1848">schaffen</word>
  <word id="word_1849">so</word>
  <word id="word_1850">gut</word>
  <word id="word_1851">gesicherte</word>
  <word id="word_1852">kleine</word>
  <word id="word_1853">Inseln</word>
  <word id="word_1854">aus</word>
  <word id="word_1855">Paradies-Feeling</word>
  <word id="word_1856">,</word>
  <word id="word_1857">lokalen</word>
  <word id="word_1858">Lustobjekten</word>
  <word id="word_1859">,</word>
  <word id="word_1860">einem</word>
  <word id="word_1861">Hauch</word>
  <word id="word_1862">von</word>
  <word id="word_1863">großer</word>
  <word id="word_1864">weiter</word>
  <word id="word_1865">Welt</word>
  <word id="word_1866">,</word>
  <word id="word_1867">schicken</word>
  <word id="word_1868">Aktivitäten</word>
  <word id="word_1869">und</word>
  <word id="word_1870">überquellenden</word>
  <word id="word_1871">Buffets</word>
  <word id="word_1872">.</word>
  <word id="word_1873">Gefällig</word>
  <word id="word_1874">wie</word>
  <word id="word_1875">ihr</word>
  <word id="word_1876">Innenleben</word>
  <word id="word_1877">ist</word>
  <word id="word_1878">auch</word>
  <word id="word_1879">die</word>
  <word id="word_1880">Architektur</word>
  <word id="word_1881">:</word>
  <word id="word_1882">lauschige</word>
  <word id="word_1883">Winkel</word>
  <word id="word_1884">,</word>
  <word id="word_1885">kommunikative</word>
  <word id="word_1886">Treffs</word>
  <word id="word_1887">,</word>
  <word id="word_1888">ansprechendes</word>
  <word id="word_1889">Design</word>
  <word id="word_1890">.</word>
  <word id="word_1891">Erst</word>
  <word id="word_1892">das</word>
  <word id="word_1893">Ensemble</word>
  <word id="word_1894">garantiert</word>
  <word id="word_1895">das</word>
  <word id="word_1896">richtige</word>
  <word id="word_1897">Urlaubsgefühl</word>
  <word id="word_1898">.</word>
  <word id="word_1899">Erst</word>
  <word id="word_1900">diese</word>
  <word id="word_1901">Gesamtinszenierung</word>
  <word id="word_1902">heiler</word>
  <word id="word_1903">,</word>
  <word id="word_1904">schöner</word>
  <word id="word_1905">Urlaubswelt</word>
  <word id="word_1906">bindet</word>
  <word id="word_1907">die</word>
  <word id="word_1908">Besucher</word>
  <word id="word_1909">.</word>
  <word id="word_1910">Die</word>
  <word id="word_1911">Einrichtung</word>
  <word id="word_1912">ist</word>
  <word id="word_1913">wie</word>
  <word id="word_1914">eine</word>
  <word id="word_1915">omnipotente</word>
  <word id="word_1916">Mama</word>
  <word id="word_1917">.</word>
  <word id="word_1918">In</word>
  <word id="word_1919">diesen</word>
  <word id="word_1920">schönen</word>
  <word id="word_1921">neuen</word>
  <word id="word_1922">Ferienwelten</word>
  <word id="word_1923">zappelt</word>
  <word id="word_1924">die</word>
  <word id="word_1925">Masse</word>
  <word id="word_1926">willig</word>
  <word id="word_1927">am</word>
  <word id="word_1928">Tropf</word>
  <word id="word_1929">der</word>
  <word id="word_1930">großen</word>
  <word id="word_1931">Spaßspender</word>
  <word id="word_1932">.</word>
  <word id="word_1933">"</word>
  <word id="word_1934">Die</word>
  <word id="word_1935">vorgefertigten</word>
  <word id="word_1936">Weltstücke</word>
  <word id="word_1937">erfüllen</word>
  <word id="word_1938">bereits</word>
  <word id="word_1939">den</word>
  <word id="word_1940">Tatbestand</word>
  <word id="word_1941">einer</word>
  <word id="word_1942">kompletten</word>
  <word id="word_1943">Simulation</word>
  <word id="word_1944">,</word>
  <word id="word_1945">lange</word>
  <word id="word_1946">bevor</word>
  <word id="word_1947">Simulationstechnologien</word>
  <word id="word_1948">sich</word>
  <word id="word_1949">der</word>
  <word id="word_1950">Erzeugung</word>
  <word id="word_1951">von</word>
  <word id="word_1952">Scheinwelten</word>
  <word id="word_1953">annehmen</word>
  <word id="word_1954">.</word>
  <word id="word_1955">Die</word>
  <word id="word_1956">Welt</word>
  <word id="word_1957">der</word>
  <word id="word_1958">käuflichen</word>
  <word id="word_1959">Fertigprodukte</word>
  <word id="word_1960">legt</word>
  <word id="word_1961">sich</word>
  <word id="word_1962">wie</word>
  <word id="word_1963">eine</word>
  <word id="word_1964">undurchdringliche</word>
  <word id="word_1965">Schicht</word>
  <word id="word_1966">von</word>
  <word id="word_1967">zäher</word>
  <word id="word_1968">Konsistenz</word>
  <word id="word_1969">über</word>
  <word id="word_1970">die</word>
  <word id="word_1971">Wirklichkeit</word>
  <word id="word_1972">,</word>
  <word id="word_1973">begräbt</word>
  <word id="word_1974">diese</word>
  <word id="word_1975">unter</word>
  <word id="word_1976">sich</word>
  <word id="word_1977">und</word>
  <word id="word_1978">schneidet</word>
  <word id="word_1979">den</word>
  <word id="word_1980">Menschen</word>
  <word id="word_1981">von</word>
  <word id="word_1982">unvermittelter</word>
  <word id="word_1983">Erfahrung</word>
  <word id="word_1984">ab</word>
  <word id="word_1985">.</word>
  <word id="word_1986">Die</word>
  <word id="word_1987">verbrauchsfertige</word>
  <word id="word_1988">Welt</word>
  <word id="word_1989">läßt</word>
  <word id="word_1990">sich</word>
  <word id="word_1991">eben</word>
  <word id="word_1992">nicht</word>
  <word id="word_1993">erfahren</word>
  <word id="word_1994">,</word>
  <word id="word_1995">sondern</word>
  <word id="word_1996">nur</word>
  <word id="word_1997">kaufen</word>
  <word id="word_1998">und</word>
  <word id="word_1999">konsumieren</word>
  <word id="word_2000">"</word>
  <word id="word_2001">,</word>
  <word id="word_2002">schreibt</word>
  <word id="word_2003">die</word>
  <word id="word_2004">Erziehungswissenschaftlerin</word>
  <word id="word_2005">Marianne</word>
  <word id="word_2006">Gronemeyer</word>
  <word id="word_2007">skeptisch</word>
  <word id="word_2008">über</word>
  <word id="word_2009">die</word>
  <word id="word_2010">Glücksproduzenten</word>
  <word id="word_2011">.</word>
  <word id="word_2012">Auch</word>
  <word id="word_2013">wenn</word>
  <word id="word_2014">man</word>
  <word id="word_2015">immer</word>
  <word id="word_2016">weiter</word>
  <word id="word_2017">fährt</word>
  <word id="word_2018">und</word>
  <word id="word_2019">fährt</word>
  <word id="word_2020">-</word>
  <word id="word_2021">die</word>
  <word id="word_2022">Welt</word>
  <word id="word_2023">im</word>
  <word id="word_2024">Ghetto</word>
  <word id="word_2025">bleibt</word>
  <word id="word_2026">sich</word>
  <word id="word_2027">gleich</word>
  <word id="word_2028">.</word>
  <word id="word_2029">Erste</word>
  <word id="word_2030">Bürgerpflicht</word>
  <word id="word_2031">:</word>
  <word id="word_2032">Konsum</word>
  <word id="word_2033">,</word>
  <word id="word_2034">Konsum</word>
  <word id="word_2035">Alles</word>
  <word id="word_2036">ist</word>
  <word id="word_2037">käuflich</word>
  <word id="word_2038">.</word>
  <word id="word_2039">Wirkliche</word>
  <word id="word_2040">Erfahrung</word>
  <word id="word_2041">ist</word>
  <word id="word_2042">es</word>
  <word id="word_2043">nicht</word>
  <word id="word_2044">.</word>
  <word id="word_2045">Jenseits</word>
  <word id="word_2046">des</word>
  <word id="word_2047">monetären</word>
  <word id="word_2048">Kreislaufs</word>
  <word id="word_2049">veröden</word>
  <word id="word_2050">die</word>
  <word id="word_2051">Erfahrungsbereiche</word>
  <word id="word_2052">,</word>
  <word id="word_2053">auch</word>
  <word id="word_2054">im</word>
  <word id="word_2055">Freizeitbereich</word>
  <word id="word_2056">.</word>
  <word id="word_2057">Alternativen</word>
  <word id="word_2058">wie</word>
  <word id="word_2059">andere</word>
  <word id="word_2060">Reiseformen</word>
  <word id="word_2061">werden</word>
  <word id="word_2062">schlicht</word>
  <word id="word_2063">in</word>
  <word id="word_2064">den</word>
  <word id="word_2065">Markt</word>
  <word id="word_2066">integriert</word>
  <word id="word_2067">.</word>
  <word id="word_2068">Soziale</word>
  <word id="word_2069">Bereiche</word>
  <word id="word_2070">brechen</word>
  <word id="word_2071">weg</word>
  <word id="word_2072">.</word>
  <word id="word_2073">Aktivitäten</word>
  <word id="word_2074">wie</word>
  <word id="word_2075">das</word>
  <word id="word_2076">soziale</word>
  <word id="word_2077">Wandern</word>
  <word id="word_2078">der</word>
  <word id="word_2079">Naturfreunde</word>
  <word id="word_2080">,</word>
  <word id="word_2081">das</word>
  <word id="word_2082">Engagement</word>
  <word id="word_2083">von</word>
  <word id="word_2084">Aktion</word>
  <word id="word_2085">Sühnezeichen</word>
  <word id="word_2086">,</word>
  <word id="word_2087">Jugend-</word>
  <word id="word_2088">,</word>
  <word id="word_2089">Begegnungs-</word>
  <word id="word_2090">und</word>
  <word id="word_2091">Austauschprogramme</word>
  <word id="word_2092">,</word>
  <word id="word_2093">gewerkschaftliche</word>
  <word id="word_2094">und</word>
  <word id="word_2095">kirchliche</word>
  <word id="word_2096">Freizeitinitiativen</word>
  <word id="word_2097">riechen</word>
  <word id="word_2098">nach</word>
  <word id="word_2099">Mottenkiste</word>
  <word id="word_2100">-</word>
  <word id="word_2101">oder</word>
  <word id="word_2102">nach</word>
  <word id="word_2103">Armut</word>
  <word id="word_2104">.</word>
  <word id="word_2105">Wer</word>
  <word id="word_2106">es</word>
  <word id="word_2107">sich</word>
  <word id="word_2108">nicht</word>
  <word id="word_2109">leisten</word>
  <word id="word_2110">kann</word>
  <word id="word_2111">,</word>
  <word id="word_2112">in</word>
  <word id="word_2113">den</word>
  <word id="word_2114">Urlaub</word>
  <word id="word_2115">zu</word>
  <word id="word_2116">fahren</word>
  <word id="word_2117">,</word>
  <word id="word_2118">kommt</word>
  <word id="word_2119">schnell</word>
  <word id="word_2120">in</word>
  <word id="word_2121">den</word>
  <word id="word_2122">Ruch</word>
  <word id="word_2123">von</word>
  <word id="word_2124">sozialer</word>
  <word id="word_2125">Randgruppe</word>
  <word id="word_2126">.</word>
  <word id="word_2127">Ein</word>
  <word id="word_2128">Frevel</word>
  <word id="word_2129">in</word>
  <word id="word_2130">unserer</word>
  <word id="word_2131">Gesellschaft</word>
  <word id="word_2132">.</word>
  <word id="word_2133">Hier</word>
  <word id="word_2134">gilt</word>
  <word id="word_2135">als</word>
  <word id="word_2136">erste</word>
  <word id="word_2137">Bürgerpflicht</word>
  <word id="word_2138">:</word>
  <word id="word_2139">Konsum</word>
  <word id="word_2140">.</word>
  <word id="word_2141">Und</word>
  <word id="word_2142">gerade</word>
  <word id="word_2143">im</word>
  <word id="word_2144">Freizeitbereich</word>
  <word id="word_2145">wird</word>
  <word id="word_2146">mehr</word>
  <word id="word_2147">und</word>
  <word id="word_2148">mehr</word>
  <word id="word_2149">konsumiert</word>
  <word id="word_2150">.</word>
  <word id="word_2151">Kein</word>
  <word id="word_2152">Wunder</word>
  <word id="word_2153">,</word>
  <word id="word_2154">hier</word>
  <word id="word_2155">lassen</word>
  <word id="word_2156">sich</word>
  <word id="word_2157">noch</word>
  <word id="word_2158">unbegrenzt</word>
  <word id="word_2159">neue</word>
  <word id="word_2160">Produkte</word>
  <word id="word_2161">umsetzen</word>
  <word id="word_2162">und</word>
  <word id="word_2163">erfinden</word>
  <word id="word_2164">.</word>
  <word id="word_2165">Sie</word>
  <word id="word_2166">kompensieren</word>
  <word id="word_2167">nicht</word>
  <word id="word_2168">zuletzt</word>
  <word id="word_2169">die</word>
  <word id="word_2170">zunehmenden</word>
  <word id="word_2171">Defizite</word>
  <word id="word_2172">im</word>
  <word id="word_2173">öffentlichen</word>
  <word id="word_2174">und</word>
  <word id="word_2175">sozialen</word>
  <word id="word_2176">Freizeitangebot</word>
  <word id="word_2177">.</word>
  <word id="word_2178">Das</word>
  <word id="word_2179">ausgeklügelte</word>
  <word id="word_2180">Spaßbad</word>
  <word id="word_2181">ersetzt</word>
  <word id="word_2182">bestens</word>
  <word id="word_2183">das</word>
  <word id="word_2184">Freibad</word>
  <word id="word_2185">um</word>
  <word id="word_2186">die</word>
  <word id="word_2187">Ecke</word>
  <word id="word_2188">,</word>
  <word id="word_2189">das</word>
  <word id="word_2190">längst</word>
  <word id="word_2191">dem</word>
  <word id="word_2192">Sparetat</word>
  <word id="word_2193">der</word>
  <word id="word_2194">Städte</word>
  <word id="word_2195">geopfert</word>
  <word id="word_2196">wurde</word>
  <word id="word_2197">.</word>
  <word id="word_2198">Das</word>
  <word id="word_2199">Spaßbad</word>
  <word id="word_2200">ist</word>
  <word id="word_2201">zwar</word>
  <word id="word_2202">nicht</word>
  <word id="word_2203">immer</word>
  <word id="word_2204">und</word>
  <word id="word_2205">schon</word>
  <word id="word_2206">gar</word>
  <word id="word_2207">nicht</word>
  <word id="word_2208">für</word>
  <word id="word_2209">jeden</word>
  <word id="word_2210">erschwinglich</word>
  <word id="word_2211">,</word>
  <word id="word_2212">aber</word>
  <word id="word_2213">dafür</word>
  <word id="word_2214">um</word>
  <word id="word_2215">so</word>
  <word id="word_2216">aufregender</word>
  <word id="word_2217">.</word>
  <word id="word_2218">Und</word>
  <word id="word_2219">Disney</word>
  <word id="word_2220">World</word>
  <word id="word_2221">wird</word>
  <word id="word_2222">zum</word>
  <word id="word_2223">multinationalen</word>
  <word id="word_2224">Kindergarten</word>
  <word id="word_2225">,</word>
  <word id="word_2226">vor</word>
  <word id="word_2227">dem</word>
  <word id="word_2228">alles</word>
  <word id="word_2229">andere</word>
  <word id="word_2230">verblaßt</word>
  <word id="word_2231">.</word>
  <word id="word_2232">Für</word>
  <word id="word_2233">den</word>
  <word id="word_2234">gesamten</word>
  <word id="word_2235">Freizeitbereich</word>
  <word id="word_2236">ist</word>
  <word id="word_2237">eine</word>
  <word id="word_2238">weitere</word>
  <word id="word_2239">Kommerzialisierung</word>
  <word id="word_2240">zu</word>
  <word id="word_2241">erwarten</word>
  <word id="word_2242">.</word>
  <word id="word_2243">Die</word>
  <word id="word_2244">Kommunen</word>
  <word id="word_2245">fördern</word>
  <word id="word_2246">gerade</word>
  <word id="word_2247">dort</word>
  <word id="word_2248">die</word>
  <word id="word_2249">Privatisierungen</word>
  <word id="word_2250">.</word>
  <word id="word_2251">Was</word>
  <word id="word_2252">so</word>
  <word id="word_2253">harmlos</word>
  <word id="word_2254">als</word>
  <word id="word_2255">Kommerzialisierung</word>
  <word id="word_2256">der</word>
  <word id="word_2257">Freizeit</word>
  <word id="word_2258">daherkommt</word>
  <word id="word_2259">,</word>
  <word id="word_2260">ist</word>
  <word id="word_2261">in</word>
  <word id="word_2262">wachsendem</word>
  <word id="word_2263">Maße</word>
  <word id="word_2264">die</word>
  <word id="word_2265">perfekte</word>
  <word id="word_2266">Vermarktung</word>
  <word id="word_2267">unserer</word>
  <word id="word_2268">Bedürfnisse</word>
  <word id="word_2269">.</word>
  <word id="word_2270">Im</word>
  <word id="word_2271">Urlaubspaket</word>
  <word id="word_2272">sind</word>
  <word id="word_2273">sie</word>
  <word id="word_2274">komprimiert</word>
  <word id="word_2275">zusammengefaßt</word>
  <word id="word_2276">.</word>
  <word id="word_2277">Doch</word>
  <word id="word_2278">der</word>
  <word id="word_2279">Seelenfrieden</word>
  <word id="word_2280">wird</word>
  <word id="word_2281">erst</word>
  <word id="word_2282">ganz</word>
  <word id="word_2283">perfekt</word>
  <word id="word_2284">,</word>
  <word id="word_2285">wenn</word>
  <word id="word_2286">beunruhigende</word>
  <word id="word_2287">fremde</word>
  <word id="word_2288">Einflüsse</word>
  <word id="word_2289">draußen</word>
  <word id="word_2290">bleiben</word>
  <word id="word_2291">.</word>
  <word id="word_2292">Denn</word>
  <word id="word_2293">wer</word>
  <word id="word_2294">verreist</word>
  <word id="word_2295">,</word>
  <word id="word_2296">verreist</word>
  <word id="word_2297">zum</word>
  <word id="word_2298">eigenen</word>
  <word id="word_2299">Genuß</word>
  <word id="word_2300">.</word>
  <word id="word_2301">In</word>
  <word id="word_2302">der</word>
  <word id="word_2303">Fremde</word>
  <word id="word_2304">bleibt</word>
  <word id="word_2305">der</word>
  <word id="word_2306">Fremde</word>
  <word id="word_2307">fremd</word>
  <word id="word_2308">,</word>
  <word id="word_2309">und</word>
  <word id="word_2310">er</word>
  <word id="word_2311">will</word>
  <word id="word_2312">es</word>
  <word id="word_2313">auch</word>
  <word id="word_2314">so</word>
  <word id="word_2315">.</word>
  <word id="word_2316">Im</word>
  <word id="word_2317">Ferienghetto</word>
  <word id="word_2318">versichert</word>
  <word id="word_2319">er</word>
  <word id="word_2320">sich</word>
  <word id="word_2321">seiner</word>
  <word id="word_2322">eigenen</word>
  <word id="word_2323">kulturellen</word>
  <word id="word_2324">Identität</word>
  <word id="word_2325">und</word>
  <word id="word_2326">Wertigkeit</word>
  <word id="word_2327">.</word>
  <word id="word_2328">Zuviel</word>
  <word id="word_2329">Nähe</word>
  <word id="word_2330">zum</word>
  <word id="word_2331">Fremden</word>
  <word id="word_2332">erschüttert</word>
  <word id="word_2333">die</word>
  <word id="word_2334">Wahrnehmung</word>
  <word id="word_2335">.</word>
  <word id="word_2336">Die</word>
  <word id="word_2337">Begegnung</word>
  <word id="word_2338">mit</word>
  <word id="word_2339">dem</word>
  <word id="word_2340">Fremden</word>
  <word id="word_2341">ist</word>
  <word id="word_2342">immer</word>
  <word id="word_2343">"</word>
  <word id="word_2344">schmerzhaft</word>
  <word id="word_2345">"</word>
  <word id="word_2346">,</word>
  <word id="word_2347">meinte</word>
  <word id="word_2348">der</word>
  <word id="word_2349">Künstler</word>
  <word id="word_2350">Beuys</word>
  <word id="word_2351">.</word>
  <word id="word_2352">Zur</word>
  <word id="word_2353">Vermeidung</word>
  <word id="word_2354">unangenehmer</word>
  <word id="word_2355">Gefühle</word>
  <word id="word_2356">durch</word>
  <word id="word_2357">zuviel</word>
  <word id="word_2358">Andersartigkeit</word>
  <word id="word_2359">muß</word>
  <word id="word_2360">der</word>
  <word id="word_2361">Kontakt</word>
  <word id="word_2362">zum</word>
  <word id="word_2363">Fremden</word>
  <word id="word_2364">auf</word>
  <word id="word_2365">ein</word>
  <word id="word_2366">verträgliches</word>
  <word id="word_2367">,</word>
  <word id="word_2368">das</word>
  <word id="word_2369">heißt</word>
  <word id="word_2370">offensichtlich</word>
  <word id="word_2371">folkloristisches</word>
  <word id="word_2372">Maß</word>
  <word id="word_2373">reduziert</word>
  <word id="word_2374">werden</word>
  <word id="word_2375">.</word>
  <word id="word_2376">Was</word>
  <word id="word_2377">bietet</word>
  <word id="word_2378">sich</word>
  <word id="word_2379">dazu</word>
  <word id="word_2380">besser</word>
  <word id="word_2381">an</word>
  <word id="word_2382">als</word>
  <word id="word_2383">die</word>
  <word id="word_2384">abgeschlossene</word>
  <word id="word_2385">Großanlage</word>
  <word id="word_2386">!</word>
  <word id="word_2387">Es</word>
  <word id="word_2388">ist</word>
  <word id="word_2389">geradezu</word>
  <word id="word_2390">perfide</word>
  <word id="word_2391">,</word>
  <word id="word_2392">diese</word>
  <word id="word_2393">immanente</word>
  <word id="word_2394">Logik</word>
  <word id="word_2395">der</word>
  <word id="word_2396">touristischen</word>
  <word id="word_2397">Veranstaltung</word>
  <word id="word_2398">im</word>
  <word id="word_2399">nachhinein</word>
  <word id="word_2400">als</word>
  <word id="word_2401">sozialverträglich</word>
  <word id="word_2402">im</word>
  <word id="word_2403">Interesse</word>
  <word id="word_2404">der</word>
  <word id="word_2405">anderen</word>
  <word id="word_2406">Kultur</word>
  <word id="word_2407">zu</word>
  <word id="word_2408">verklären</word>
  <word id="word_2409">.</word>
  <word id="word_2410">Zwischen</word>
  <word id="word_2411">den</word>
  <word id="word_2412">touristischen</word>
  <word id="word_2413">Produzenten</word>
  <word id="word_2414">und</word>
  <word id="word_2415">Konsumenten</word>
  <word id="word_2416">gibt</word>
  <word id="word_2417">es</word>
  <word id="word_2418">eine</word>
  <word id="word_2419">elementare</word>
  <word id="word_2420">Interessenübereinstimmung</word>
  <word id="word_2421">:</word>
  <word id="word_2422">sich</word>
  <word id="word_2423">abzuschotten</word>
  <word id="word_2424">gegen</word>
  <word id="word_2425">alle</word>
  <word id="word_2426">Einflüsse</word>
  <word id="word_2427">,</word>
  <word id="word_2428">die</word>
  <word id="word_2429">die</word>
  <word id="word_2430">Urlaubsidylle</word>
  <word id="word_2431">und</word>
  <word id="word_2432">den</word>
  <word id="word_2433">reibungslosen</word>
  <word id="word_2434">Freizeitkonsum</word>
  <word id="word_2435">stören</word>
  <word id="word_2436">könnten</word>
  <word id="word_2437">.</word>
</words>
