<?xml version="1.0" encoding="ISO-8859-1"?>
<!DOCTYPE words SYSTEM "words.dtd">
<words>
  <word id="word_1">"</word>
  <word id="word_2">Ratzfatz</word>
  <word id="word_3">sauber</word>
  <word id="word_4">"</word>
  <word id="word_5">Hamburger</word>
  <word id="word_6">Behinderte</word>
  <word id="word_7">protestieren</word>
  <word id="word_8">gegen</word>
  <word id="word_9">neue</word>
  <word id="word_10">Pflegeversicherung</word>
  <word id="word_11">/</word>
  <word id="word_12">Morgen</word>
  <word id="word_13">Demo</word>
  <word id="word_14">Von</word>
  <word id="word_15">Patricia</word>
  <word id="word_16">Faller</word>
  <word id="word_17">"</word>
  <word id="word_18">Gegen</word>
  <word id="word_19">eine</word>
  <word id="word_20">Ratzfatz-Satt-und-Sauber-Versorgung</word>
  <word id="word_21">"</word>
  <word id="word_22">nach</word>
  <word id="word_23">der</word>
  <word id="word_24">neuen</word>
  <word id="word_25">Pflegeversicherung</word>
  <word id="word_26">wollen</word>
  <word id="word_27">morgen</word>
  <word id="word_28">Hamburger</word>
  <word id="word_29">Behinderte</word>
  <word id="word_30">protestieren</word>
  <word id="word_31">.</word>
  <word id="word_32">Das</word>
  <word id="word_33">,</word>
  <word id="word_34">Jahrhundertwerk</word>
  <word id="word_35">'</word>
  <word id="word_36">Pflegeversicherung</word>
  <word id="word_37">entpuppe</word>
  <word id="word_38">sich</word>
  <word id="word_39">mehr</word>
  <word id="word_40">und</word>
  <word id="word_41">mehr</word>
  <word id="word_42">als</word>
  <word id="word_43">massiver</word>
  <word id="word_44">Angriff</word>
  <word id="word_45">auf</word>
  <word id="word_46">die</word>
  <word id="word_47">soziale</word>
  <word id="word_48">Absicherung</word>
  <word id="word_49">und</word>
  <word id="word_50">die</word>
  <word id="word_51">Lebensqualität</word>
  <word id="word_52">behinderter</word>
  <word id="word_53">Menschen</word>
  <word id="word_54">,</word>
  <word id="word_55">heißt</word>
  <word id="word_56">es</word>
  <word id="word_57">in</word>
  <word id="word_58">einem</word>
  <word id="word_59">Demo-Aufruf</word>
  <word id="word_60">des</word>
  <word id="word_61">Behindertenvereins</word>
  <word id="word_62">"</word>
  <word id="word_63">Autonom</word>
  <word id="word_64">Leben</word>
  <word id="word_65">"</word>
  <word id="word_66">.</word>
  <word id="word_67">"</word>
  <word id="word_68">Behinderte</word>
  <word id="word_69">kommen</word>
  <word id="word_70">selten</word>
  <word id="word_71">auf</word>
  <word id="word_72">die</word>
  <word id="word_73">Idee</word>
  <word id="word_74">,</word>
  <word id="word_75">sich</word>
  <word id="word_76">zu</word>
  <word id="word_77">wehren</word>
  <word id="word_78">"</word>
  <word id="word_79">,</word>
  <word id="word_80">erklärt</word>
  <word id="word_81">Vereinsmitglied</word>
  <word id="word_82">,</word>
  <word id="word_83">Gerlef</word>
  <word id="word_84">Gleiss</word>
  <word id="word_85">,</word>
  <word id="word_86">"</word>
  <word id="word_87">doch</word>
  <word id="word_88">jetzt</word>
  <word id="word_89">reicht's</word>
  <word id="word_90">.</word>
  <word id="word_91">"</word>
  <word id="word_92">"</word>
  <word id="word_93">Hamburg</word>
  <word id="word_94">ist</word>
  <word id="word_95">die</word>
  <word id="word_96">Stadt</word>
  <word id="word_97">,</word>
  <word id="word_98">in</word>
  <word id="word_99">der</word>
  <word id="word_100">die</word>
  <word id="word_101">meisten</word>
  <word id="word_102">Pflegeversicherungsanträge</word>
  <word id="word_103">abgelehnt</word>
  <word id="word_104">und</word>
  <word id="word_105">die</word>
  <word id="word_106">wenigsten</word>
  <word id="word_107">Bedürftigen</word>
  <word id="word_108">in</word>
  <word id="word_109">die</word>
  <word id="word_110">höchste</word>
  <word id="word_111">Pflegekategorie</word>
  <word id="word_112">eingestuft</word>
  <word id="word_113">werden</word>
  <word id="word_114">"</word>
  <word id="word_115">,</word>
  <word id="word_116">berichtet</word>
  <word id="word_117">Gleiss</word>
  <word id="word_118">,</word>
  <word id="word_119">der</word>
  <word id="word_120">selbst</word>
  <word id="word_121">im</word>
  <word id="word_122">Rollstuhl</word>
  <word id="word_123">sitzt</word>
  <word id="word_124">.</word>
  <word id="word_125">Er</word>
  <word id="word_126">weiß</word>
  <word id="word_127">von</word>
  <word id="word_128">Querschnittsgelähmten</word>
  <word id="word_129">,</word>
  <word id="word_130">die</word>
  <word id="word_131">bisher</word>
  <word id="word_132">ein</word>
  <word id="word_133">Höchstpflegegeld</word>
  <word id="word_134">von</word>
  <word id="word_135">1031</word>
  <word id="word_136">Mark</word>
  <word id="word_137">erhielten</word>
  <word id="word_138">und</word>
  <word id="word_139">jetzt</word>
  <word id="word_140">nicht</word>
  <word id="word_141">mal</word>
  <word id="word_142">mehr</word>
  <word id="word_143">in</word>
  <word id="word_144">die</word>
  <word id="word_145">unterste</word>
  <word id="word_146">Pflegekategorie</word>
  <word id="word_147">eingestuft</word>
  <word id="word_148">wurden</word>
  <word id="word_149">.</word>
  <word id="word_150">Denn</word>
  <word id="word_151">im</word>
  <word id="word_152">strengen</word>
  <word id="word_153">Sinne</word>
  <word id="word_154">sind</word>
  <word id="word_155">sie</word>
  <word id="word_156">nicht</word>
  <word id="word_157">pflegebedürftig</word>
  <word id="word_158">,</word>
  <word id="word_159">ebensowenig</word>
  <word id="word_160">wie</word>
  <word id="word_161">viele</word>
  <word id="word_162">geistig</word>
  <word id="word_163">Behinderte</word>
  <word id="word_164">.</word>
  <word id="word_165">Sie</word>
  <word id="word_166">können</word>
  <word id="word_167">sich</word>
  <word id="word_168">-</word>
  <word id="word_169">wenn</word>
  <word id="word_170">auch</word>
  <word id="word_171">unter</word>
  <word id="word_172">großen</word>
  <word id="word_173">Anstrengungen</word>
  <word id="word_174">-</word>
  <word id="word_175">selbst</word>
  <word id="word_176">helfen</word>
  <word id="word_177">.</word>
  <word id="word_178">Gleiss'</word>
  <word id="word_179">Ansicht</word>
  <word id="word_180">nach</word>
  <word id="word_181">müßte</word>
  <word id="word_182">der</word>
  <word id="word_183">Behindertenbegriff</word>
  <word id="word_184">weiter</word>
  <word id="word_185">gefaßt</word>
  <word id="word_186">werden</word>
  <word id="word_187">,</word>
  <word id="word_188">als</word>
  <word id="word_189">es</word>
  <word id="word_190">das</word>
  <word id="word_191">Pflegeversicherungsgesetz</word>
  <word id="word_192">tut</word>
  <word id="word_193">.</word>
  <word id="word_194">Denn</word>
  <word id="word_195">genauso</word>
  <word id="word_196">wichtig</word>
  <word id="word_197">wie</word>
  <word id="word_198">die</word>
  <word id="word_199">pflegerischen</word>
  <word id="word_200">Hilfen</word>
  <word id="word_201">seien</word>
  <word id="word_202">soziale</word>
  <word id="word_203">Leistungen</word>
  <word id="word_204">.</word>
  <word id="word_205">Wenn</word>
  <word id="word_206">ein</word>
  <word id="word_207">Behinderter</word>
  <word id="word_208">beispielsweise</word>
  <word id="word_209">Begleitung</word>
  <word id="word_210">zur</word>
  <word id="word_211">Arbeit</word>
  <word id="word_212">oder</word>
  <word id="word_213">ins</word>
  <word id="word_214">Kino</word>
  <word id="word_215">brauche</word>
  <word id="word_216">,</word>
  <word id="word_217">dann</word>
  <word id="word_218">sollte</word>
  <word id="word_219">auch</word>
  <word id="word_220">das</word>
  <word id="word_221">finanziert</word>
  <word id="word_222">werden</word>
  <word id="word_223">.</word>
  <word id="word_224">Ein</word>
  <word id="word_225">weiteres</word>
  <word id="word_226">Manko</word>
  <word id="word_227">sei</word>
  <word id="word_228">,</word>
  <word id="word_229">daß</word>
  <word id="word_230">die</word>
  <word id="word_231">Besitzstandsregelung</word>
  <word id="word_232">in</word>
  <word id="word_233">Hamburg</word>
  <word id="word_234">noch</word>
  <word id="word_235">nicht</word>
  <word id="word_236">greife</word>
  <word id="word_237">.</word>
  <word id="word_238">Danach</word>
  <word id="word_239">sollte</word>
  <word id="word_240">kein</word>
  <word id="word_241">Behinderter</word>
  <word id="word_242">weniger</word>
  <word id="word_243">Geld</word>
  <word id="word_244">zur</word>
  <word id="word_245">Verfügung</word>
  <word id="word_246">haben</word>
  <word id="word_247">als</word>
  <word id="word_248">vor</word>
  <word id="word_249">der</word>
  <word id="word_250">Pflegeversicherung</word>
  <word id="word_251">.</word>
  <word id="word_252">Mitte</word>
  <word id="word_253">August</word>
  <word id="word_254">hatte</word>
  <word id="word_255">die</word>
  <word id="word_256">Behörde</word>
  <word id="word_257">für</word>
  <word id="word_258">Arbeit</word>
  <word id="word_259">,</word>
  <word id="word_260">Gesundheit</word>
  <word id="word_261">und</word>
  <word id="word_262">Soziales</word>
  <word id="word_263">das</word>
  <word id="word_264">zwar</word>
  <word id="word_265">beschlossen</word>
  <word id="word_266">,</word>
  <word id="word_267">doch</word>
  <word id="word_268">die</word>
  <word id="word_269">Sozialämter</word>
  <word id="word_270">kämpfen</word>
  <word id="word_271">noch</word>
  <word id="word_272">mit</word>
  <word id="word_273">der</word>
  <word id="word_274">EDV-Umstellung</word>
  <word id="word_275">.</word>
  <word id="word_276">"</word>
  <word id="word_277">Im</word>
  <word id="word_278">Laufe</word>
  <word id="word_279">des</word>
  <word id="word_280">Novembers</word>
  <word id="word_281">hoffen</word>
  <word id="word_282">wir</word>
  <word id="word_283">,</word>
  <word id="word_284">das</word>
  <word id="word_285">Problem</word>
  <word id="word_286">im</word>
  <word id="word_287">Griff</word>
  <word id="word_288">zu</word>
  <word id="word_289">haben</word>
  <word id="word_290">"</word>
  <word id="word_291">,</word>
  <word id="word_292">heißt</word>
  <word id="word_293">es</word>
  <word id="word_294">beispielsweise</word>
  <word id="word_295">beim</word>
  <word id="word_296">Sozialamt</word>
  <word id="word_297">des</word>
  <word id="word_298">Bezirks</word>
  <word id="word_299">Mitte</word>
  <word id="word_300">.</word>
  <word id="word_301">Eine</word>
  <word id="word_302">Argumentation</word>
  <word id="word_303">,</word>
  <word id="word_304">die</word>
  <word id="word_305">Gerlef</word>
  <word id="word_306">Gleiss</word>
  <word id="word_307">ärgert</word>
  <word id="word_308">:</word>
  <word id="word_309">"</word>
  <word id="word_310">Die</word>
  <word id="word_311">Ämter</word>
  <word id="word_312">wissen</word>
  <word id="word_313">gar</word>
  <word id="word_314">nicht</word>
  <word id="word_315">,</word>
  <word id="word_316">was</word>
  <word id="word_317">das</word>
  <word id="word_318">für</word>
  <word id="word_319">die</word>
  <word id="word_320">Betroffenen</word>
  <word id="word_321">bedeutet</word>
  <word id="word_322">.</word>
  <word id="word_323">"</word>
  <word id="word_324">Einige</word>
  <word id="word_325">Behinderte</word>
  <word id="word_326">hätten</word>
  <word id="word_327">seit</word>
  <word id="word_328">April</word>
  <word id="word_329">über</word>
  <word id="word_330">1000</word>
  <word id="word_331">Mark</word>
  <word id="word_332">im</word>
  <word id="word_333">Monat</word>
  <word id="word_334">weniger</word>
  <word id="word_335">zur</word>
  <word id="word_336">Verfügung</word>
  <word id="word_337">,</word>
  <word id="word_338">weil</word>
  <word id="word_339">die</word>
  <word id="word_340">Pflegeversicherung</word>
  <word id="word_341">nur</word>
  <word id="word_342">für</word>
  <word id="word_343">die</word>
  <word id="word_344">rein</word>
  <word id="word_345">pflegerischen</word>
  <word id="word_346">Hilfen</word>
  <word id="word_347">zahlt</word>
  <word id="word_348">und</word>
  <word id="word_349">das</word>
  <word id="word_350">Sozialamt</word>
  <word id="word_351">für</word>
  <word id="word_352">den</word>
  <word id="word_353">Rest</word>
  <word id="word_354">nicht</word>
  <word id="word_355">aufkommt</word>
  <word id="word_356">.</word>
  <word id="word_357">Viele</word>
  <word id="word_358">müßten</word>
  <word id="word_359">sich</word>
  <word id="word_360">deshalb</word>
  <word id="word_361">verschulden</word>
  <word id="word_362">oder</word>
  <word id="word_363">ihre</word>
  <word id="word_364">Hilfskräfte</word>
  <word id="word_365">entlassen</word>
  <word id="word_366">.</word>
  <word id="word_367">Doch</word>
  <word id="word_368">neben</word>
  <word id="word_369">der</word>
  <word id="word_370">finanziellen</word>
  <word id="word_371">Verschlechterung</word>
  <word id="word_372">sind</word>
  <word id="word_373">vor</word>
  <word id="word_374">allem</word>
  <word id="word_375">auch</word>
  <word id="word_376">Errungenschaften</word>
  <word id="word_377">wie</word>
  <word id="word_378">mehr</word>
  <word id="word_379">Selbstbestimmung</word>
  <word id="word_380">und</word>
  <word id="word_381">soziale</word>
  <word id="word_382">Integration</word>
  <word id="word_383">gefährdet</word>
  <word id="word_384">.</word>
  <word id="word_385">So</word>
  <word id="word_386">gab</word>
  <word id="word_387">es</word>
  <word id="word_388">bisher</word>
  <word id="word_389">die</word>
  <word id="word_390">Möglichkeit</word>
  <word id="word_391">,</word>
  <word id="word_392">daß</word>
  <word id="word_393">Behinderte</word>
  <word id="word_394">als</word>
  <word id="word_395">Arbeitgeber</word>
  <word id="word_396">ihre</word>
  <word id="word_397">Hilfskräfte</word>
  <word id="word_398">selbst</word>
  <word id="word_399">aussuchten</word>
  <word id="word_400">und</word>
  <word id="word_401">beschäftigten</word>
  <word id="word_402">.</word>
  <word id="word_403">Mit</word>
  <word id="word_404">der</word>
  <word id="word_405">Pflegeversicherung</word>
  <word id="word_406">ist</word>
  <word id="word_407">das</word>
  <word id="word_408">passe</word>
  <word id="word_409">,</word>
  <word id="word_410">weil</word>
  <word id="word_411">deren</word>
  <word id="word_412">Pflegesätze</word>
  <word id="word_413">dafür</word>
  <word id="word_414">nicht</word>
  <word id="word_415">ausreichen</word>
  <word id="word_416">.</word>
  <word id="word_417">Sollte</word>
  <word id="word_418">sich</word>
  <word id="word_419">der</word>
  <word id="word_420">Behinderte</word>
  <word id="word_421">für</word>
  <word id="word_422">die</word>
  <word id="word_423">Sachleistungen</word>
  <word id="word_424">entscheiden</word>
  <word id="word_425">,</word>
  <word id="word_426">dann</word>
  <word id="word_427">kann</word>
  <word id="word_428">er</word>
  <word id="word_429">sich</word>
  <word id="word_430">seine</word>
  <word id="word_431">Helfer</word>
  <word id="word_432">nicht</word>
  <word id="word_433">selbst</word>
  <word id="word_434">auswählen</word>
  <word id="word_435">.</word>
  <word id="word_436">Den</word>
  <word id="word_437">Betroffenen</word>
  <word id="word_438">rät</word>
  <word id="word_439">Gleiss</word>
  <word id="word_440">,</word>
  <word id="word_441">auf</word>
  <word id="word_442">jeden</word>
  <word id="word_443">Fall</word>
  <word id="word_444">Widerspruch</word>
  <word id="word_445">gegen</word>
  <word id="word_446">Bescheide</word>
  <word id="word_447">vom</word>
  <word id="word_448">Sozialamt</word>
  <word id="word_449">einzulegen</word>
  <word id="word_450">,</word>
  <word id="word_451">die</word>
  <word id="word_452">sie</word>
  <word id="word_453">schlechter</word>
  <word id="word_454">stellen</word>
  <word id="word_455">.</word>
  <word id="word_456">Klagen</word>
  <word id="word_457">sollten</word>
  <word id="word_458">sie</word>
  <word id="word_459">auch</word>
  <word id="word_460">gegen</word>
  <word id="word_461">die</word>
  <word id="word_462">Begutachtung</word>
  <word id="word_463">.</word>
  <word id="word_464">Denn</word>
  <word id="word_465">es</word>
  <word id="word_466">bestehe</word>
  <word id="word_467">berechtigte</word>
  <word id="word_468">Hoffnung</word>
  <word id="word_469">,</word>
  <word id="word_470">so</word>
  <word id="word_471">Gleiss</word>
  <word id="word_472">,</word>
  <word id="word_473">daß</word>
  <word id="word_474">die</word>
  <word id="word_475">Sozialgerichte</word>
  <word id="word_476">den</word>
  <word id="word_477">Behindertenbegriff</word>
  <word id="word_478">weiterfassen</word>
  <word id="word_479">würden</word>
  <word id="word_480">.</word>
  <word id="word_481">Demo-Treffpunkt</word>
  <word id="word_482">:</word>
  <word id="word_483">morgen</word>
  <word id="word_484">,</word>
  <word id="word_485">16</word>
  <word id="word_486">Uhr</word>
  <word id="word_487">,</word>
  <word id="word_488">U-Bahn</word>
  <word id="word_489">Hamburger</word>
  <word id="word_490">Straße</word>
</words>
