<?xml version="1.0" encoding="ISO-8859-1"?>
<!DOCTYPE markables SYSTEM "markables.dtd">
<markables xmlns="www.eml.org/NameSpaces/markable">
<markable id="markable_5" span="word_1" mmax_level="markable" gend="masc" head_pos="0" markable_type="np" min_ids="word_1" num="sing" sem_type="None" sentenceid="1"/>
<markable id="markable_13" span="word_2..word_4" mmax_level="markable" gend="masc" head_pos="1" markable_type="np" min_ids="word_2" num="sing" sem_type="EVT" sentenceid="2"/>
<markable id="markable_14" span="word_4" mmax_level="markable" gend="fem" head_pos="3" markable_type="np" min_ids="word_4" num="plur" sem_type="EVT" sentenceid="2"/>
<markable id="markable_62" span="word_5" mmax_level="markable" gend="neut" head_pos="4" markable_type="np" min_ids="word_5" num="sing" sem_type="LOC" sentenceid="3"/>
<markable id="markable_63" span="word_7" mmax_level="markable" gend="fem" head_pos="6" markable_type="np" min_ids="word_7" num="sing" sem_type="None" sentenceid="3"/>
<markable id="markable_64" span="word_10..word_12" mmax_level="markable" gend="fem" head_pos="11" markable_type="np" min_ids="word_10..word_12" num="sing" sem_type="ORG" sentenceid="3"/>
<markable id="markable_65" span="word_17" mmax_level="markable" head_pos="16" markable_type="np" mention_type="pro.refl" min_ids="word_17" sentenceid="3"/>
<markable id="markable_66" span="word_19..word_23" mmax_level="markable" gend="fem" head_pos="19" markable_type="np" min_ids="word_19..word_20" num="sing" sem_type="EVT" sentenceid="3"/>
<markable id="markable_67" span="word_22..word_23" mmax_level="markable" gend="masc" head_pos="21" markable_type="np" min_ids="word_22" num="sing" sem_type="PER" sentenceid="3"/>
<markable id="markable_122" span="word_28" mmax_level="markable" gend="masc" head_pos="27" markable_type="np" min_ids="word_28" num="sing" sem_type="TMP" sentenceid="4"/>
<markable id="markable_123" span="word_30..word_41" mmax_level="markable" gend="masc" head_pos="30" markable_type="np" min_ids="word_30..word_31" num="sing" sem_type="PER" sentenceid="4"/>
<markable id="markable_124" span="word_33..word_41" mmax_level="markable" gend="neut" head_pos="32" markable_type="np" min_ids="word_33" num="sing" sem_type="None" sentenceid="4"/>
<markable id="markable_125" span="word_36" mmax_level="markable" gend="masc" head_pos="35" markable_type="np" min_ids="word_36" num="sing" sem_type="None" sentenceid="4"/>
<markable id="markable_126" span="word_38..word_39" mmax_level="markable" gend="masc" head_pos="38" markable_type="np" min_ids="word_38..word_39" num="sing" sem_type="TMP" sentenceid="4"/>
<markable id="markable_127" span="word_43..word_49" mmax_level="markable" gend="fem" head_pos="43" markable_type="np" min_ids="word_43..word_44" num="sing" sem_type="EVT" sentenceid="4"/>
<markable id="markable_128" span="word_45..word_46" mmax_level="markable" gend="fem" head_pos="45" markable_type="np" min_ids="word_45..word_46" num="plur" sem_type="EVT" sentenceid="4"/>
<markable id="markable_129" span="word_48..word_49" mmax_level="markable" gend="neut" head_pos="48" markable_type="np" min_ids="word_48..word_49" num="sing" sem_type="ORG" sentenceid="4"/>
<markable id="markable_201" span="word_52..word_54" mmax_level="markable" gend="fem" head_pos="53" markable_type="np" min_ids="word_52..word_54" num="sing" sem_type="EVT" sentenceid="5"/>
<markable id="markable_202" span="word_60" mmax_level="markable" gend="fem" head_pos="59" markable_type="np" mention_type="pro.per3" min_ids="word_60" num="sing" sentenceid="5"/>
<markable id="markable_203" span="word_63..word_64" mmax_level="markable" gend="masc" head_pos="63" markable_type="np" min_ids="word_63..word_64" num="sing" sem_type="EVT" sentenceid="5"/>
<markable id="markable_204" span="word_69..word_75" mmax_level="markable" gend="masc" head_pos="70" markable_type="np" min_ids="word_69..word_71" num="sing" sem_type="PER" sentenceid="5"/>
<markable id="markable_205" span="word_77..word_78" mmax_level="markable" gend="fem" head_pos="77" markable_type="np" min_ids="word_77..word_78" num="sing" sem_type="EVT" sentenceid="5"/>
<markable id="markable_206" span="word_80" mmax_level="markable" head_pos="79" markable_type="poss" mention_type="pro.per3" min_ids="word_80" sentenceid="5"/>
<markable id="markable_207" span="word_80..word_81" mmax_level="markable" gend="fem" head_pos="80" markable_type="np" min_ids="word_80..word_81" num="sing" sem_type="TMP" sentenceid="5"/>
<markable id="markable_255" span="word_87..word_90" mmax_level="markable" gend="masc" head_pos="87" markable_type="np" min_ids="word_87..word_88" num="sing" sem_type="PER" sentenceid="6"/>
<markable id="markable_256" span="word_89..word_90" mmax_level="markable" gend="neut" head_pos="89" markable_type="np" min_ids="word_89..word_90" num="sing" sem_type="ORG" sentenceid="6"/>
<markable id="markable_257" span="word_93..word_96" mmax_level="markable" gend="fem" head_pos="93" markable_type="np" min_ids="word_93..word_94" num="sing" sem_type="EVT" sentenceid="6"/>
<markable id="markable_258" span="word_95..word_96" mmax_level="markable" gend="fem" head_pos="95" markable_type="np" min_ids="word_95..word_96" num="plur" sem_type="EVT" sentenceid="6"/>
<markable id="markable_259" span="word_98..word_102" mmax_level="markable" gend="fem" head_pos="101" markable_type="np" min_ids="word_98..word_102" num="sing" sem_type="EVT" sentenceid="6"/>
</markables>
